{"learner":{"attributes":{"scikit_learn":"{\"n_estimators\": 100, \"objective\": \"reg:squarederror\", \"max_depth\": null, \"learning_rate\": null, \"verbosity\": null, \"booster\": null, \"tree_method\": null, \"gamma\": null, \"min_child_weight\": null, \"max_delta_step\": null, \"subsample\": null, \"colsample_bytree\": null, \"colsample_bylevel\": null, \"colsample_bynode\": null, \"reg_alpha\": null, \"reg_lambda\": null, \"scale_pos_weight\": null, \"base_score\": null, \"missing\": NaN, \"num_parallel_tree\": null, \"kwargs\": {}, \"random_state\": 42, \"n_jobs\": null, \"monotone_constraints\": null, \"interaction_constraints\": null, \"importance_type\": \"gain\", \"gpu_id\": null, \"validate_parameters\": null, \"n_features_in_\": 4, \"type\": \"XGBRegressor\"}"},"gradient_booster":{"model":{"gbtree_model_param":{"num_trees":"100","size_leaf_vector":"0"},"tree_info":[0,0,0,0,0,0,0,0,0,0,0,0,0,0,0,0,0,0,0,0,0,0,0,0,0,0,0,0,0,0,0,0,0,0,0,0,0,0,0,0,0,0,0,0,0,0,0,0,0,0,0,0,0,0,0,0,0,0,0,0,0,0,0,0,0,0,0,0,0,0,0,0,0,0,0,0,0,0,0,0,0,0,0,0,0,0,0,0,0,0,0,0,0,0,0,0,0,0,0,0],"trees":[{"base_weights":[7.4794516E-2,4.9912497E-1,-4.3551724E-2,1.2535E0,4.227272E-2,-3.807857E-1,2.6245162E-1,-4.3313637E-1,-1.6185714E-1],"default_left":[true,true,true,false,false,true,false,false,false],"id":0,"leaf_child_counts":[0,0,0,0,0,0,0,0,0],"left_children":[1,3,5,-1,-1,7,-1,-1,-1],"loss_changes":[3.6876454E0,5.4612184E0,6.0852323E0,0E0,0E0,2.50803E-1,0E0,0E0,0E0],"parents":[2147483647,0,0,1,1,2,2,5,5],"right_children":[2,4,6,-1,-1,8,-1,-1,-1],"split_conditions":[6.1934985E2,1.270093E1,1.5601544E2,3.7605003E-1,1.2681817E-2,9.8368126E1,7.8735486E-2,-1.2994091E-1,-4.8557144E-2],"split_indices":[1,0,0,0,0,0,0,0,0],"sum_hessian":[7.2E1,1.5E1,5.7E1,5E0,1E1,2.7E1,3E1,2.1E1,6E0],"tree_param":{"num_deleted":"0","num_feature":"4","num_nodes":"9","size_leaf_vector":"0"}},{"base_weights":[5.631465E-2,3.736832E-1,-3.2206237E-2,9.40125E-1,3.0743776E-2,-2.7292493E-1,1.8625599E-1,-3.0910185E-1,-1.2023675E-1],"default_left":[true,true,true,false,false,true,false,false,false],"id":1,"leaf_child_counts":[0,0,0,0,0,0,0,0,0],"left_children":[1,3,5,-1,-1,7,-1,-1,-1],"loss_changes":[2.0628784E0,3.0791802E0,3.1009345E0,0E0,0E0,1.1750078E-1,0E0,0E0,0E0],"parents":[2147483647,0,0,1,1,2,2,5,5],"right_children":[2,4,6,-1,-1,8,-1,-1,-1],"split_conditions":[6.1934985E2,1.270093E1,1.5601544E2,2.820375E-1,9.223133E-3,9.8368126E1,5.58768E-2,-9.273056E-2,-3.6071025E-2],"split_indices":[1,0,0,0,0,0,0,0,0],"sum_hessian":[7.2E1,1.5E1,5.7E1,5E0,1E1,2.7E1,3E1,2.1E1,6E0],"tree_param":{"num_deleted":"0","num_feature":"4","num_nodes":"9","size_leaf_vector":"0"}},{"base_weights":[4.2411167E-2,2.7978206E-1,-2.3801684E-2,7.0509374E-1,2.2359135E-2,-1.956475E-1,1.3218169E-1,-2.2058631E-1,-8.9318715E-2],"default_left":[true,true,true,false,false,true,false,false,false],"id":2,"leaf_child_counts":[0,0,0,0,0,0,0,0,0],"left_children":[1,3,5,-1,-1,7,-1,-1,-1],"loss_changes":[1.1540005E0,1.735994E0,1.5805563E0,0E0,0E0,5.4545403E-2,0E0,0E0,0E0],"parents":[2147483647,0,0,1,1,2,2,5,5],"right_children":[2,4,6,-1,-1,8,-1,-1,-1],"split_conditions":[6.1934985E2,1.270093E1,1.5601544E2,2.1152814E-1,6.7077405E-3,9.8368126E1,3.965451E-2,-6.61759E-2,-2.6795616E-2],"split_indices":[1,0,0,0,0,0,0,0,0],"sum_hessian":[7.2E1,1.5E1,5.7E1,5E0,1E1,2.7E1,3E1,2.1E1,6E0],"tree_param":{"num_deleted":"0","num_feature":"4","num_nodes":"9","size_leaf_vector":"0"}},{"base_weights":[3.1946987E-2,2.0948717E-1,-1.7580425E-2,5.288203E-1,1.6261201E-2,-1.4027365E-1,9.380637E-2,-1.5599048E-1,-5.6646843E-2],"default_left":[true,true,true,false,false,true,false,false,false],"id":3,"leaf_child_counts":[0,0,0,0,0,0,0,0,0],"left_children":[1,3,5,-1,-1,7,-1,-1,-1],"loss_changes":[6.455796E-1,9.7865593E-1,8.0581003E-1,0E0,0E0,2.7965426E-2,0E0,0E0,0E0],"parents":[2147483647,0,0,1,1,2,2,5,5],"right_children":[2,4,6,-1,-1,8,-1,-1,-1],"split_conditions":[6.1934985E2,1.270093E1,1.5601544E2,1.5864609E-1,4.878361E-3,8.4165204E2,2.8141912E-2,-4.6797145E-2,-1.6994053E-2],"split_indices":[1,0,0,0,0,1,0,0,0],"sum_hessian":[7.2E1,1.5E1,5.7E1,5E0,1E1,2.7E1,3E1,2.2E1,5E0],"tree_param":{"num_deleted":"0","num_feature":"4","num_nodes":"9","size_leaf_vector":"0"}},{"base_weights":[2.4114601E-2,1.568613E-1,-1.2920947E-2,3.9661518E-1,1.1826345E-2,-1.0046981E-1,6.657226E-2,-1.3457584E-1,-7.048497E-2,-7.861115E-2,-4.248513E-2],"default_left":[true,true,true,false,false,true,false,false,true,false,false],"id":4,"leaf_child_counts":[0,0,0,0,0,0,0,0,0,0,0],"left_children":[1,3,5,-1,-1,7,-1,-1,9,-1,-1],"loss_changes":[3.6092013E-1,5.516726E-1,4.1034177E-1,0E0,0E0,1.9149005E-2,0E0,0E0,5.2823126E-4,0E0,0E0],"parents":[2147483647,0,0,1,1,2,2,5,5,8,8],"right_children":[2,4,6,-1,-1,8,-1,-1,10,-1,-1],"split_conditions":[6.1934985E2,1.270093E1,1.5601544E2,1.1898456E-1,3.5479036E-3,4.3247475E1,1.9971678E-2,-4.0372755E-2,8.377274E2,-2.3583347E-2,-1.274554E-2],"split_indices":[1,0,0,0,0,0,0,0,1,0,0],"sum_hessian":[7.2E1,1.5E1,5.7E1,5E0,1E1,2.7E1,3E1,1.1E1,1.6E1,1.1E1,5E0],"tree_param":{"num_deleted":"0","num_feature":"4","num_nodes":"11","size_leaf_vector":"0"}},{"base_weights":[1.7781626E-2,1.1746117E-1,-1.0022758E-2,2.9746133E-1,8.600974E-3,-7.306821E-2,4.7244836E-2,-9.7567484E-2,-5.147647E-2,-5.6993075E-2,-3.1863853E-2],"default_left":[true,true,true,false,false,true,false,false,true,false,false],"id":5,"leaf_child_counts":[0,0,0,0,0,0,0,0,0,0,0],"left_children":[1,3,5,-1,-1,7,-1,-1,9,-1,-1],"loss_changes":[2.0349886E-1,3.1095916E-1,2.1285884E-1,0E0,0E0,9.7890645E-3,0E0,0E0,2.329424E-5,0E0,0E0],"parents":[2147483647,0,0,1,1,2,2,5,5,8,8],"right_children":[2,4,6,-1,-1,8,-1,-1,10,-1,-1],"split_conditions":[6.1934985E2,1.270093E1,1.5601544E2,8.9238405E-2,2.5802925E-3,4.3247475E1,1.4173451E-2,-2.9270247E-2,8.377274E2,-1.7097924E-2,-9.559156E-3],"split_indices":[1,0,0,0,0,0,0,0,1,0,0],"sum_hessian":[7.2E1,1.5E1,5.7E1,5E0,1E1,2.7E1,3E1,1.1E1,1.6E1,1.1E1,5E0],"tree_param":{"num_deleted":"0","num_feature":"4","num_nodes":"11","size_leaf_vector":"0"}},{"base_weights":[1.3132958E-2,8.796149E-2,-7.7358256E-3,2.23096E-1,6.255261E-3,-5.314515E-2,3.3528592E-2,-7.073642E-2,-3.7601594E-2],"default_left":[true,true,true,false,false,true,false,false,false],"id":6,"leaf_child_counts":[0,0,0,0,0,0,0,0,0],"left_children":[1,3,5,-1,-1,7,-1,-1,-1],"loss_changes":[1.1467582E-1,1.7526576E-1,1.1046167E-1,0E0,0E0,4.9962625E-3,0E0,0E0,0E0],"parents":[2147483647,0,0,1,1,2,2,5,5],"right_children":[2,4,6,-1,-1,8,-1,-1,-1],"split_conditions":[6.1934985E2,1.270093E1,1.5601544E2,6.6928804E-2,1.8765784E-3,4.3247475E1,1.0058578E-2,-2.1220928E-2,-1.1280479E-2],"split_indices":[1,0,0,0,0,0,0,0,0],"sum_hessian":[7.2E1,1.5E1,5.7E1,5E0,1E1,2.7E1,3E1,1.1E1,1.6E1],"tree_param":{"num_deleted":"0","num_feature":"4","num_nodes":"9","size_leaf_vector":"0"}},{"base_weights":[9.828164E-3,6.587335E-2,-5.802028E-3,1.6732194E-1,4.5492677E-3,-3.836237E-2,2.3794476E-2,-5.1283907E-2,-2.6984675E-2,-3.0979544E-2,-1.4497493E-2],"default_left":[true,true,true,false,false,true,false,false,true,false,false],"id":7,"leaf_child_counts":[0,0,0,0,0,0,0,0,0,0,0],"left_children":[1,3,5,-1,-1,7,-1,-1,9,-1,-1],"loss_changes":[6.432998E-2,9.877868E-2,5.6805804E-2,0E0,0E0,2.7326047E-3,0E0,0E0,3.989134E-4,0E0,0E0],"parents":[2147483647,0,0,1,1,2,2,5,5,8,8],"right_children":[2,4,6,-1,-1,8,-1,-1,10,-1,-1],"split_conditions":[6.1934985E2,1.270093E1,1.5601544E2,5.0196584E-2,1.3647804E-3,4.3247475E1,7.138343E-3,-1.5385172E-2,8.377274E2,-9.293864E-3,-4.349248E-3],"split_indices":[1,0,0,0,0,0,0,0,1,0,0],"sum_hessian":[7.2E1,1.5E1,5.7E1,5E0,1E1,2.7E1,3E1,1.1E1,1.6E1,1.1E1,5E0],"tree_param":{"num_deleted":"0","num_feature":"4","num_nodes":"11","size_leaf_vector":"0"}},{"base_weights":[7.286172E-3,4.933396E-2,-4.4388417E-3,1.2549151E-1,3.3085698E-3,-2.7890382E-2,1.6886381E-2,-3.7180834E-2,-1.9691806E-2,-2.2999872E-2,-1.16803E-2],"default_left":[true,true,true,false,false,true,false,false,true,false,false],"id":8,"leaf_child_counts":[0,0,0,0,0,0,0,0,0,0,0],"left_children":[1,3,5,-1,-1,7,-1,-1,9,-1,-1],"loss_changes":[3.6208782E-2,5.5667713E-2,2.947731E-2,0E0,0E0,1.4005583E-3,0E0,0E0,1.8189847E-4,0E0,0E0],"parents":[2147483647,0,0,1,1,2,2,5,5,8,8],"right_children":[2,4,6,-1,-1,8,-1,-1,10,-1,-1],"split_conditions":[6.1934985E2,1.270093E1,1.5601544E2,3.7647456E-2,9.92571E-4,4.3247475E1,5.0659147E-3,-1.115425E-2,9.8368126E1,-6.8999617E-3,-3.5040902E-3],"split_indices":[1,0,0,0,0,0,0,0,0,0,0],"sum_hessian":[7.2E1,1.5E1,5.7E1,5E0,1E1,2.7E1,3E1,1.1E1,1.6E1,1E1,6E0],"tree_param":{"num_deleted":"0","num_feature":"4","num_nodes":"11","size_leaf_vector":"0"}},{"base_weights":[5.403703E-3,3.6948733E-2,-3.391542E-3,9.411857E-2,2.4062097E-3,-2.0293206E-2,1.1983881E-2,-2.6956104E-2,-1.4396265E-2,-1.612676E-2,-3.2387525E-2,-1.6418194E-2,-7.953028E-3],"default_left":[true,true,true,false,false,true,false,true,true,false,false,false,false],"id":9,"leaf_child_counts":[0,0,0,0,0,0,0,0,0,0,0,0,0],"left_children":[1,3,5,-1,-1,7,-1,9,11,-1,-1,-1,-1],"loss_changes":[2.0378893E-2,3.137018E-2,1.5315664E-2,0E0,0E0,7.120734E-4,0E0,1.8351898E-4,9.0898015E-5,0E0,0E0,0E0,0E0],"parents":[2147483647,0,0,1,1,2,2,5,5,7,7,8,8],"right_children":[2,4,6,-1,-1,8,-1,10,12,-1,-1,-1,-1],"split_conditions":[6.1934985E2,1.270093E1,1.5601544E2,2.8235573E-2,7.2186295E-4,4.3247475E1,3.5951643E-3,3.3192127E0,8.377274E2,-4.838028E-3,-9.716257E-3,-4.9254587E-3,-2.3859085E-3],"split_indices":[1,0,0,0,0,0,0,0,1,0,0,0,0],"sum_hessian":[7.2E1,1.5E1,5.7E1,5E0,1E1,2.7E1,3E1,1.1E1,1.6E1,5E0,6E0,1.1E1,5E0],"tree_param":{"num_deleted":"0","num_feature":"4","num_nodes":"13","size_leaf_vector":"0"}},{"base_weights":[3.9289854E-3,2.7673962E-2,-2.689094E-3,7.058897E-2,1.7499626E-3,-1.4986158E-2,8.504678E-3,-2.0082131E-2,-1.05074635E-2,-1.2095071E-2,-2.4059305E-2,-1.224949E-2,-6.268927E-3],"default_left":[true,true,true,false,false,true,false,true,true,false,false,false,false],"id":10,"leaf_child_counts":[0,0,0,0,0,0,0,0,0,0,0,0,0],"left_children":[1,3,5,-1,-1,7,-1,9,11,-1,-1,-1,-1],"loss_changes":[1.1546086E-2,1.7676927E-2,8.1111835E-3,0E0,0E0,4.280405E-4,0E0,9.019207E-5,4.8730755E-5,0E0,0E0,0E0,0E0],"parents":[2147483647,0,0,1,1,2,2,5,5,7,7,8,8],"right_children":[2,4,6,-1,-1,8,-1,10,12,-1,-1,-1,-1],"split_conditions":[6.1934985E2,1.270093E1,1.5601544E2,2.1176692E-2,5.249888E-4,4.3247475E1,2.5514034E-3,3.3192127E0,9.8368126E1,-3.6285215E-3,-7.217792E-3,-3.6748473E-3,-1.8806781E-3],"split_indices":[1,0,0,0,0,0,0,0,0,0,0,0,0],"sum_hessian":[7.2E1,1.5E1,5.7E1,5E0,1E1,2.7E1,3E1,1.1E1,1.6E1,5E0,6E0,1E1,6E0],"tree_param":{"num_deleted":"0","num_feature":"4","num_nodes":"13","size_leaf_vector":"0"}},{"base_weights":[2.8578471E-3,2.0728113E-2,-2.1211547E-3,5.29417E-2,1.2726919E-3,-1.1076091E-2,6.035599E-3,-1.4961351E-2,-7.6820194E-3,-9.071303E-3,-1.7872628E-2,-8.908718E-3,-4.6569193E-3],"default_left":[true,true,true,false,false,true,false,true,true,false,false,false,false],"id":11,"leaf_child_counts":[0,0,0,0,0,0,0,0,0,0,0,0,0],"left_children":[1,3,5,-1,-1,7,-1,9,11,-1,-1,-1,-1],"loss_changes":[6.539222E-3,9.960285E-3,4.3033566E-3,0E0,0E0,2.5429833E-4,0E0,4.3642707E-5,2.1597836E-5,0E0,0E0,0E0,0E0],"parents":[2147483647,0,0,1,1,2,2,5,5,7,7,8,8],"right_children":[2,4,6,-1,-1,8,-1,10,12,-1,-1,-1,-1],"split_conditions":[6.1934985E2,1.270093E1,1.5601544E2,1.588251E-2,3.818076E-4,4.3247475E1,1.8106798E-3,3.3192127E0,9.8368126E1,-2.721391E-3,-5.3617884E-3,-2.6726155E-3,-1.3970758E-3],"split_indices":[1,0,0,0,0,0,0,0,0,0,0,0,0],"sum_hessian":[7.2E1,1.5E1,5.7E1,5E0,1E1,2.7E1,3E1,1.1E1,1.6E1,5E0,6E0,1E1,6E0],"tree_param":{"num_deleted":"0","num_feature":"4","num_nodes":"13","size_leaf_vector":"0"}},{"base_weights":[2.0816233E-3,1.5526192E-2,-1.6631132E-3,3.970629E-2,9.2557614E-4,-8.187296E-3,4.2833453E-3,-1.1146544E-2,-5.6168097E-3,-6.8034763E-3,-1.3276809E-2,-6.4790696E-3,-3.459428E-3],"default_left":[true,true,true,false,false,true,false,true,true,false,false,false,false],"id":12,"leaf_child_counts":[0,0,0,0,0,0,0,0,0,0,0,0,0],"left_children":[1,3,5,-1,-1,7,-1,9,11,-1,-1,-1,-1],"loss_changes":[3.7011066E-3,5.611958E-3,2.2852244E-3,0E0,0E0,1.5037961E-4,0E0,2.069422E-5,9.209965E-6,0E0,0E0,0E0,0E0],"parents":[2147483647,0,0,1,1,2,2,5,5,7,7,8,8],"right_children":[2,4,6,-1,-1,8,-1,10,12,-1,-1,-1,-1],"split_conditions":[6.1934985E2,1.270093E1,1.5601544E2,1.1911888E-2,2.7767287E-4,4.3247475E1,1.2850036E-3,3.3192127E0,9.8368126E1,-2.041043E-3,-3.9830427E-3,-1.943721E-3,-1.0378284E-3],"split_indices":[1,0,0,0,0,0,0,0,0,0,0,0,0],"sum_hessian":[7.2E1,1.5E1,5.7E1,5E0,1E1,2.7E1,3E1,1.1E1,1.6E1,5E0,6E0,1E1,6E0],"tree_param":{"num_deleted":"0","num_feature":"4","num_nodes":"13","size_leaf_vector":"0"}},{"base_weights":[1.5183463E-3,1.1630172E-2,-1.2973014E-3,2.9779732E-2,6.731234E-4,-6.052735E-3,3.0397773E-3,-8.304588E-3,-4.1071484E-3,-5.102608E-3,-9.862772E-3,-4.6342374E-3,-2.3684453E-3],"default_left":[true,true,true,false,false,true,false,true,true,false,false,false,false],"id":13,"leaf_child_counts":[0,0,0,0,0,0,0,0,0,0,0,0,0],"left_children":[1,3,5,-1,-1,7,-1,9,11,-1,-1,-1,-1],"loss_changes":[2.0934956E-3,3.1618043E-3,1.2146309E-3,0E0,0E0,8.85647E-5,0E0,9.545416E-6,4.603731E-6,0E0,0E0,0E0,0E0],"parents":[2147483647,0,0,1,1,2,2,5,5,7,7,8,8],"right_children":[2,4,6,-1,-1,8,-1,10,12,-1,-1,-1,-1],"split_conditions":[6.1934985E2,1.270093E1,1.5601544E2,8.93392E-3,2.0193703E-4,4.3247475E1,9.119332E-4,3.3192127E0,8.377274E2,-1.5307824E-3,-2.9588318E-3,-1.3902712E-3,-7.105336E-4],"split_indices":[1,0,0,0,0,0,0,0,1,0,0,0,0],"sum_hessian":[7.2E1,1.5E1,5.7E1,5E0,1E1,2.7E1,3E1,1.1E1,1.6E1,5E0,6E0,1.1E1,5E0],"tree_param":{"num_deleted":"0","num_feature":"4","num_nodes":"13","size_leaf_vector":"0"}},{"base_weights":[1.1101996E-3,8.712122E-3,-1.0060238E-3,2.2334835E-2,4.895411E-4,-4.472284E-3,2.157244E-3,-6.187346E-3,-2.9985765E-3,-3.826957E-3,-7.32663E-3,-3.4481667E-3,-1.8637095E-3],"default_left":[true,true,true,false,false,true,false,true,true,false,false,false,false],"id":14,"leaf_child_counts":[0,0,0,0,0,0,0,0,0,0,0,0,0],"left_children":[1,3,5,-1,-1,7,-1,9,11,-1,-1,-1,-1],"loss_changes":[1.1831424E-3,1.7812878E-3,6.456009E-4,0E0,0E0,5.2216754E-5,0E0,4.231144E-6,2.2474414E-6,0E0,0E0,0E0,0E0],"parents":[2147483647,0,0,1,1,2,2,5,5,7,7,8,8],"right_children":[2,4,6,-1,-1,8,-1,10,12,-1,-1,-1,-1],"split_conditions":[6.1934985E2,1.270093E1,1.5601544E2,6.7004506E-3,1.4686234E-4,4.3247475E1,6.471732E-4,3.3192127E0,9.8368126E1,-1.1480871E-3,-2.197989E-3,-1.03445E-3,-5.591129E-4],"split_indices":[1,0,0,0,0,0,0,0,0,0,0,0,0],"sum_hessian":[7.2E1,1.5E1,5.7E1,5E0,1E1,2.7E1,3E1,1.1E1,1.6E1,5E0,6E0,1E1,6E0],"tree_param":{"num_deleted":"0","num_feature":"4","num_nodes":"13","size_leaf_vector":"0"}},{"base_weights":[8.121379E-4,6.5264646E-3,-7.7823043E-4,1.675119E-2,3.5602666E-4,-3.3070112E-3,1.5309338E-3,-4.609981E-3,-2.1927375E-3,-2.870217E-3,-5.442639E-3],"default_left":[true,true,true,false,false,true,false,true,false,false,false],"id":15,"leaf_child_counts":[0,0,0,0,0,0,0,0,0,0,0],"left_children":[1,3,5,-1,-1,7,-1,9,-1,-1,-1],"loss_changes":[6.684947E-4,1.0034926E-3,3.4374627E-4,0E0,0E0,3.0543742E-5,0E0,1.761975E-6,8.566494E-7,0E0,0E0],"parents":[2147483647,0,0,1,1,2,2,5,5,7,7],"right_children":[2,4,6,-1,-1,8,-1,10,-1,-1,-1],"split_conditions":[6.1934985E2,1.270093E1,1.5601544E2,5.0253575E-3,1.06808E-4,4.3247475E1,4.5928016E-4,3.3192127E0,-6.578213E-4,-8.610651E-4,-1.6327917E-3],"split_indices":[1,0,0,0,0,0,0,0,0,0,0],"sum_hessian":[7.2E1,1.5E1,5.7E1,5E0,1E1,2.7E1,3E1,1.1E1,1.6E1,5E0,6E0],"tree_param":{"num_deleted":"0","num_feature":"4","num_nodes":"11","size_leaf_vector":"0"}},{"base_weights":[6.019249E-4,4.889274E-3,-5.911701E-4,1.2563367E-2,2.5892528E-4,-2.4274671E-3,1.0864908E-3,-3.434808E-3,-1.5736108E-3,-1.9097369E-3,-8.206112E-4],"default_left":[true,true,true,false,false,true,false,false,true,false,false],"id":16,"leaf_child_counts":[0,0,0,0,0,0,0,0,0,0,0],"left_children":[1,3,5,-1,-1,7,-1,-1,9,-1,-1],"loss_changes":[3.763011E-4,5.652867E-4,1.8131708E-4,0E0,0E0,1.8678416E-5,0E0,6.5563654E-7,2.7355964E-6,0E0,0E0],"parents":[2147483647,0,0,1,1,2,2,5,5,8,8],"right_children":[2,4,6,-1,-1,8,-1,-1,10,-1,-1],"split_conditions":[6.1934985E2,1.270093E1,1.5601544E2,3.7690103E-3,7.7677585E-5,4.3247475E1,3.2594724E-4,-1.0304424E-3,9.8368126E1,-5.7292107E-4,-2.4618336E-4],"split_indices":[1,0,0,0,0,0,0,0,0,0,0],"sum_hessian":[7.2E1,1.5E1,5.7E1,5E0,1E1,2.7E1,3E1,1.1E1,1.6E1,1E1,6E0],"tree_param":{"num_deleted":"0","num_feature":"4","num_nodes":"11","size_leaf_vector":"0"}},{"base_weights":[4.5318156E-4,3.662901E-3,-4.4007174E-4,9.422481E-3,1.8832088E-4,-1.7652797E-3,7.710861E-4,-2.4902355E-3,-1.1497061E-3,-1.2939597E-3,-3.159867E-3,-1.3889007E-3,-6.095852E-4],"default_left":[true,true,true,false,false,true,false,true,true,false,false,false,false],"id":17,"leaf_child_counts":[0,0,0,0,0,0,0,0,0,0,0,0,0],"left_children":[1,3,5,-1,-1,7,-1,9,11,-1,-1,-1,-1],"loss_changes":[2.109097E-4,3.1841948E-4,9.445326E-5,0E0,0E0,9.632342E-6,0E0,5.5240234E-6,1.3496447E-6,0E0,0E0,0E0,0E0],"parents":[2147483647,0,0,1,1,2,2,5,5,7,7,8,8],"right_children":[2,4,6,-1,-1,8,-1,10,12,-1,-1,-1,-1],"split_conditions":[6.1934985E2,1.270093E1,1.5601544E2,2.8267445E-3,5.6496265E-5,4.3247475E1,2.3132583E-4,3.3192127E0,9.8368126E1,-3.881879E-4,-9.479601E-4,-4.1667023E-4,-1.8287556E-4],"split_indices":[1,0,0,0,0,0,0,0,0,0,0,0,0],"sum_hessian":[7.2E1,1.5E1,5.7E1,5E0,1E1,2.7E1,3E1,1.1E1,1.6E1,5E0,6E0,1E1,6E0],"tree_param":{"num_deleted":"0","num_feature":"4","num_nodes":"13","size_leaf_vector":"0"}},{"base_weights":[3.3337998E-4,2.7442444E-3,-3.37434E-4,7.0669055E-3,1.3695251E-4,-1.3048282E-3,5.472264E-4,-1.8545105E-3,-8.400626E-4,-9.704695E-4,-2.3473299E-3],"default_left":[true,true,true,false,false,true,false,true,false,false,false],"id":18,"leaf_child_counts":[0,0,0,0,0,0,0,0,0,0,0],"left_children":[1,3,5,-1,-1,7,-1,9,-1,-1,-1],"loss_changes":[1.1898463E-4,1.793592E-4,5.0351326E-5,0E0,0E0,5.5953533E-6,0E0,2.9500552E-6,6.936152E-7,0E0,0E0],"parents":[2147483647,0,0,1,1,2,2,5,5,7,7],"right_children":[2,4,6,-1,-1,8,-1,10,-1,-1,-1],"split_conditions":[6.1934985E2,1.270093E1,1.5601544E2,2.1200718E-3,4.1085754E-5,4.3247475E1,1.6416793E-4,3.3192127E0,-2.520188E-4,-2.9114087E-4,-7.0419896E-4],"split_indices":[1,0,0,0,0,0,0,0,0,0,0],"sum_hessian":[7.2E1,1.5E1,5.7E1,5E0,1E1,2.7E1,3E1,1.1E1,1.6E1,5E0,6E0],"tree_param":{"num_deleted":"0","num_feature":"4","num_nodes":"11","size_leaf_vector":"0"}},{"base_weights":[2.4814444E-4,2.0560715E-3,-2.5487243E-4,5.300224E-3,9.961833E-5,-1.1154021E-3,3.0199025E-4,-7.9106673E-4,-1.7437307E-3,-1.9463897E-4,3.8837042E-4],"default_left":[true,true,true,false,false,true,true,false,false,false,false],"id":19,"leaf_child_counts":[0,0,0,0,0,0,0,0,0,0,0],"left_children":[1,3,5,-1,-1,7,9,-1,-1,-1,-1],"loss_changes":[6.691154E-5,1.01024525E-4,2.813026E-5,0E0,0E0,3.307743E-6,1.6199526E-6,0E0,0E0,0E0,0E0],"parents":[2147483647,0,0,1,1,2,2,5,5,6,6],"right_children":[2,4,6,-1,-1,8,10,-1,-1,-1,-1],"split_conditions":[6.1934985E2,1.270093E1,8.277668E2,1.5900672E-3,2.98855E-5,6.896179E2,1.4697641E2,-2.3732003E-4,-5.2311923E-4,-5.839169E-5,1.1651113E-4],"split_indices":[1,0,1,0,0,1,0,0,0,0,0],"sum_hessian":[7.2E1,1.5E1,5.7E1,5E0,1E1,2.2E1,3.5E1,1.6E1,6E0,5E0,3E1],"tree_param":{"num_deleted":"0","num_feature":"4","num_nodes":"11","size_leaf_vector":"0"}},{"base_weights":[1.8627312E-4,1.5405286E-3,-1.9052622E-4,3.9752126E-3,7.247112E-5,-8.393498E-4,2.0041014E-4,-5.8739353E-4,-1.2953428E-3,-1.6123056E-4,2.7560611E-4],"default_left":[true,true,true,false,false,true,true,false,false,false,false],"id":20,"leaf_child_counts":[0,0,0,0,0,0,0,0,0,0,0],"left_children":[1,3,5,-1,-1,7,9,-1,-1,-1,-1],"loss_changes":[3.7544138E-5,5.6900008E-5,1.487984E-5,0E0,0E0,1.7667116E-6,1.0506114E-6,0E0,0E0,0E0,0E0],"parents":[2147483647,0,0,1,1,2,2,5,5,6,6],"right_children":[2,4,6,-1,-1,8,10,-1,-1,-1,-1],"split_conditions":[6.1934985E2,1.270093E1,9.8368126E1,1.1925638E-3,2.1741336E-5,6.896179E2,1.5601544E2,-1.7621806E-4,-3.8860287E-4,-4.8369173E-5,8.2681836E-5],"split_indices":[1,0,0,0,0,1,0,0,0,0,0],"sum_hessian":[7.2E1,1.5E1,5.7E1,5E0,1E1,2.1E1,3.6E1,1.5E1,6E0,6E0,3E1],"tree_param":{"num_deleted":"0","num_feature":"4","num_nodes":"11","size_leaf_vector":"0"}},{"base_weights":[1.3975886E-4,1.4171817E-3,-8.550162E-5,-3.83238E-4,2.9814045E-3,-9.622547E-4,2.3669842E-5,-1.7460519E-4,1.9559744E-4],"default_left":[true,true,true,false,false,false,true,false,false],"id":21,"leaf_child_counts":[0,0,0,0,0,0,0,0,0],"left_children":[1,3,5,-1,-1,-1,7,-1,-1],"loss_changes":[2.1127133E-5,3.2121417E-5,6.052911E-6,0E0,0E0,0E0,1.9772226E-6,8.559864E-7,0E0],"parents":[2147483647,0,0,1,1,2,2,6,6],"right_children":[2,4,6,-1,-1,-1,8,-1,-1],"split_conditions":[4.5189133E0,1.5882642E0,1.4431877E1,-1.149714E-4,8.944214E-4,-2.886764E-4,1.5601544E2,-5.2381558E-5,5.8679234E-5],"split_indices":[0,0,0,0,0,0,0,0,0],"sum_hessian":[7.2E1,1E1,6.2E1,5E0,5E0,6E0,5.6E1,2.6E1,3E1],"tree_param":{"num_deleted":"0","num_feature":"4","num_nodes":"9","size_leaf_vector":"0"}},{"base_weights":[1.0466267E-4,9.075273E-4,-1.18621756E-4,2.2361476E-3,1.00322744E-4,-4.845459E-4,1.0216075E-4],"default_left":[true,true,true,false,false,false,false],"id":22,"leaf_child_counts":[0,0,0,0,0,0,0],"left_children":[1,3,5,-1,-1,-1,-1],"loss_changes":[1.3194155E-5,1.6935159E-5,4.735301E-6,0E0,0E0,4.1108478E-7,2.5062894E-7],"parents":[2147483647,0,0,1,1,2,2],"right_children":[2,4,6,-1,-1,-1,-1],"split_conditions":[6.1934985E2,1.270093E1,9.8368126E1,6.7084434E-4,3.0096824E-5,-1.4536377E-4,3.064823E-5],"split_indices":[1,0,0,0,0,0,0],"sum_hessian":[7.2E1,1.5E1,5.7E1,5E0,1E1,2.1E1,3.6E1],"tree_param":{"num_deleted":"0","num_feature":"4","num_nodes":"7","size_leaf_vector":"0"}},{"base_weights":[8.129466E-5,6.790552E-4,-8.500644E-5,1.6770562E-3,7.295879E-5,-3.3869417E-4,7.943312E-5],"default_left":[true,true,true,false,false,false,false],"id":23,"leaf_child_counts":[0,0,0,0,0,0,0],"left_children":[1,3,5,-1,-1,-1,-1],"loss_changes":[7.3145256E-6,9.5558025E-6,2.446449E-6,0E0,0E0,5.874024E-7,1.8843866E-7],"parents":[2147483647,0,0,1,1,2,2],"right_children":[2,4,6,-1,-1,-1,-1],"split_conditions":[6.1934985E2,1.270093E1,8.277668E2,5.0311687E-4,2.1887638E-5,-1.0160825E-4,2.3829938E-5],"split_indices":[1,0,1,0,0,0,0],"sum_hessian":[7.2E1,1.5E1,5.7E1,5E0,1E1,2.2E1,3.5E1],"tree_param":{"num_deleted":"0","num_feature":"4","num_nodes":"7","size_leaf_vector":"0"}},{"base_weights":[6.3032574E-5,6.415742E-4,-3.898315E-5,-8.1617385E-5,1.2578368E-3,-5.031276E-4,1.8700957E-5],"default_left":[true,true,true,false,false,false,false],"id":24,"leaf_child_counts":[0,0,0,0,0,0,0],"left_children":[1,3,5,-1,-1,-1,-1],"loss_changes":[4.3334962E-6,5.005097E-6,1.6961558E-6,0E0,0E0,0E0,3.0521807E-7],"parents":[2147483647,0,0,1,1,2,2],"right_children":[2,4,6,-1,-1,-1,-1],"split_conditions":[4.5189133E0,1.5882642E0,1.4431877E1,-2.4485216E-5,3.7735107E-4,-1.5093829E-4,5.610287E-6],"split_indices":[0,0,0,0,0,0,0],"sum_hessian":[7.2E1,1E1,6.2E1,5E0,5E0,6E0,5.6E1],"tree_param":{"num_deleted":"0","num_feature":"4","num_nodes":"7","size_leaf_vector":"0"}},{"base_weights":[4.696601E-5,4.8115087E-4,-2.9589537E-5,-6.121304E-5,9.4332296E-4],"default_left":[true,true,false,false,false],"id":25,"leaf_child_counts":[0,0,0,0,0],"left_children":[1,3,-1,-1,-1],"loss_changes":[2.4407032E-6,2.815064E-6,9.3259763E-7,0E0,0E0],"parents":[2147483647,0,0,1,1],"right_children":[2,4,-1,-1,-1],"split_conditions":[4.5189133E0,1.5882642E0,-8.876861E-6,-1.8363913E-5,2.829969E-4],"split_indices":[0,0,0,0,0],"sum_hessian":[7.2E1,1E1,6.2E1,5E0,5E0],"tree_param":{"num_deleted":"0","num_feature":"4","num_nodes":"5","size_leaf_vector":"0"}},{"base_weights":[3.6379806E-5,3.03844E-4,-3.8030652E-5,7.074873E-4,5.605275E-5,-1.7762996E-4,8.928584E-5],"default_left":[true,true,true,false,false,false,false],"id":26,"leaf_child_counts":[0,0,0,0,0,0,0],"left_children":[1,3,5,-1,-1,-1,-1],"loss_changes":[1.4644111E-6,1.5606518E-6,1.0467108E-6,0E0,0E0,1.5204012E-7,0E0],"parents":[2147483647,0,0,1,1,2,2],"right_children":[2,4,6,-1,-1,-1,-1],"split_conditions":[6.1934985E2,1.270093E1,1.5601544E2,2.1224619E-4,1.6815826E-5,-5.328899E-5,2.6785752E-5],"split_indices":[1,0,0,0,0,0,0],"sum_hessian":[7.2E1,1.5E1,5.7E1,5E0,1E1,2.7E1,3E1],"tree_param":{"num_deleted":"0","num_feature":"4","num_nodes":"7","size_leaf_vector":"0"}},{"base_weights":[2.8256021E-5],"default_left":[false],"id":27,"leaf_child_counts":[0],"left_children":[-1],"loss_changes":[8.7774134E-7],"parents":[2147483647],"right_children":[-1],"split_conditions":[8.476807E-6],"split_indices":[0],"sum_hessian":[7.2E1],"tree_param":{"num_deleted":"0","num_feature":"4","num_nodes":"1","size_leaf_vector":"0"}},{"base_weights":[1.9895933E-5],"default_left":[false],"id":28,"leaf_child_counts":[0],"left_children":[-1],"loss_changes":[8.814607E-7],"parents":[2147483647],"right_children":[-1],"split_conditions":[5.9687804E-6],"split_indices":[0],"sum_hessian":[7.2E1],"tree_param":{"num_deleted":"0","num_feature":"4","num_nodes":"1","size_leaf_vector":"0"}},{"base_weights":[1.40148995E-5],"default_left":[false],"id":29,"leaf_child_counts":[0],"left_children":[-1],"loss_changes":[8.8422183E-7],"parents":[2147483647],"right_children":[-1],"split_conditions":[4.20447E-6],"split_indices":[0],"sum_hessian":[7.2E1],"tree_param":{"num_deleted":"0","num_feature":"4","num_nodes":"1","size_leaf_vector":"0"}},{"base_weights":[9.849157E-6],"default_left":[false],"id":30,"leaf_child_counts":[0],"left_children":[-1],"loss_changes":[8.859963E-7],"parents":[2147483647],"right_children":[-1],"split_conditions":[2.9547473E-6],"split_indices":[0],"sum_hessian":[7.2E1],"tree_param":{"num_deleted":"0","num_feature":"4","num_nodes":"1","size_leaf_vector":"0"}},{"base_weights":[6.924013E-6],"default_left":[false],"id":31,"leaf_child_counts":[0],"left_children":[-1],"loss_changes":[8.876856E-7],"parents":[2147483647],"right_children":[-1],"split_conditions":[2.077204E-6],"split_indices":[0],"sum_hessian":[7.2E1],"tree_param":{"num_deleted":"0","num_feature":"4","num_nodes":"1","size_leaf_vector":"0"}},{"base_weights":[4.866352E-6],"default_left":[false],"id":32,"leaf_child_counts":[0],"left_children":[-1],"loss_changes":[8.884557E-7],"parents":[2147483647],"right_children":[-1],"split_conditions":[1.4599057E-6],"split_indices":[0],"sum_hessian":[7.2E1],"tree_param":{"num_deleted":"0","num_feature":"4","num_nodes":"1","size_leaf_vector":"0"}},{"base_weights":[3.4444136E-6],"default_left":[false],"id":33,"leaf_child_counts":[0],"left_children":[-1],"loss_changes":[8.890686E-7],"parents":[2147483647],"right_children":[-1],"split_conditions":[1.0333241E-6],"split_indices":[0],"sum_hessian":[7.2E1],"tree_param":{"num_deleted":"0","num_feature":"4","num_nodes":"1","size_leaf_vector":"0"}},{"base_weights":[2.438917E-6],"default_left":[false],"id":34,"leaf_child_counts":[0],"left_children":[-1],"loss_changes":[8.896769E-7],"parents":[2147483647],"right_children":[-1],"split_conditions":[7.3167513E-7],"split_indices":[0],"sum_hessian":[7.2E1],"tree_param":{"num_deleted":"0","num_feature":"4","num_nodes":"1","size_leaf_vector":"0"}},{"base_weights":[1.7263914E-6],"default_left":[false],"id":35,"leaf_child_counts":[0],"left_children":[-1],"loss_changes":[8.8998297E-7],"parents":[2147483647],"right_children":[-1],"split_conditions":[5.1791744E-7],"split_indices":[0],"sum_hessian":[7.2E1],"tree_param":{"num_deleted":"0","num_feature":"4","num_nodes":"1","size_leaf_vector":"0"}},{"base_weights":[1.2103621E-6],"default_left":[false],"id":36,"leaf_child_counts":[0],"left_children":[-1],"loss_changes":[8.9037303E-7],"parents":[2147483647],"right_children":[-1],"split_conditions":[3.6310865E-7],"split_indices":[0],"sum_hessian":[7.2E1],"tree_param":{"num_deleted":"0","num_feature":"4","num_nodes":"1","size_leaf_vector":"0"}},{"base_weights":[8.4760563E-7],"default_left":[false],"id":37,"leaf_child_counts":[0],"left_children":[-1],"loss_changes":[8.9021097E-7],"parents":[2147483647],"right_children":[-1],"split_conditions":[2.542817E-7],"split_indices":[0],"sum_hessian":[7.2E1],"tree_param":{"num_deleted":"0","num_feature":"4","num_nodes":"1","size_leaf_vector":"0"}},{"base_weights":[6.0551275E-7],"default_left":[false],"id":38,"leaf_child_counts":[0],"left_children":[-1],"loss_changes":[8.903095E-7],"parents":[2147483647],"right_children":[-1],"split_conditions":[1.8165383E-7],"split_indices":[0],"sum_hessian":[7.2E1],"tree_param":{"num_deleted":"0","num_feature":"4","num_nodes":"1","size_leaf_vector":"0"}},{"base_weights":[4.26163E-7],"default_left":[false],"id":39,"leaf_child_counts":[0],"left_children":[-1],"loss_changes":[8.902095E-7],"parents":[2147483647],"right_children":[-1],"split_conditions":[1.278489E-7],"split_indices":[0],"sum_hessian":[7.2E1],"tree_param":{"num_deleted":"0","num_feature":"4","num_nodes":"1","size_leaf_vector":"0"}},{"base_weights":[2.948593E-7],"default_left":[false],"id":40,"leaf_child_counts":[0],"left_children":[-1],"loss_changes":[8.899592E-7],"parents":[2147483647],"right_children":[-1],"split_conditions":[8.845779E-8],"split_indices":[0],"sum_hessian":[7.2E1],"tree_param":{"num_deleted":"0","num_feature":"4","num_nodes":"1","size_leaf_vector":"0"}},{"base_weights":[2.3091697E-7],"default_left":[false],"id":41,"leaf_child_counts":[0],"left_children":[-1],"loss_changes":[8.9011485E-7],"parents":[2147483647],"right_children":[-1],"split_conditions":[6.9275096E-8],"split_indices":[0],"sum_hessian":[7.2E1],"tree_param":{"num_deleted":"0","num_feature":"4","num_nodes":"1","size_leaf_vector":"0"}},{"base_weights":[1.7547138E-7],"default_left":[false],"id":42,"leaf_child_counts":[0],"left_children":[-1],"loss_changes":[8.9027566E-7],"parents":[2147483647],"right_children":[-1],"split_conditions":[5.264142E-8],"split_indices":[0],"sum_hessian":[7.2E1],"tree_param":{"num_deleted":"0","num_feature":"4","num_nodes":"1","size_leaf_vector":"0"}},{"base_weights":[1.2119952E-7],"default_left":[false],"id":43,"leaf_child_counts":[0],"left_children":[-1],"loss_changes":[8.904781E-7],"parents":[2147483647],"right_children":[-1],"split_conditions":[3.6359857E-8],"split_indices":[0],"sum_hessian":[7.2E1],"tree_param":{"num_deleted":"0","num_feature":"4","num_nodes":"1","size_leaf_vector":"0"}},{"base_weights":[7.3816885E-8],"default_left":[false],"id":44,"leaf_child_counts":[0],"left_children":[-1],"loss_changes":[8.906803E-7],"parents":[2147483647],"right_children":[-1],"split_conditions":[2.2145066E-8],"split_indices":[0],"sum_hessian":[7.2E1],"tree_param":{"num_deleted":"0","num_feature":"4","num_nodes":"1","size_leaf_vector":"0"}},{"base_weights":[6.4937424E-8],"default_left":[false],"id":45,"leaf_child_counts":[0],"left_children":[-1],"loss_changes":[8.9067083E-7],"parents":[2147483647],"right_children":[-1],"split_conditions":[1.9481227E-8],"split_indices":[0],"sum_hessian":[7.2E1],"tree_param":{"num_deleted":"0","num_feature":"4","num_nodes":"1","size_leaf_vector":"0"}},{"base_weights":[5.6542763E-8],"default_left":[false],"id":46,"leaf_child_counts":[0],"left_children":[-1],"loss_changes":[8.906696E-7],"parents":[2147483647],"right_children":[-1],"split_conditions":[1.696283E-8],"split_indices":[0],"sum_hessian":[7.2E1],"tree_param":{"num_deleted":"0","num_feature":"4","num_nodes":"1","size_leaf_vector":"0"}},{"base_weights":[4.9474917E-8],"default_left":[false],"id":47,"leaf_child_counts":[0],"left_children":[-1],"loss_changes":[8.906629E-7],"parents":[2147483647],"right_children":[-1],"split_conditions":[1.4842476E-8],"split_indices":[0],"sum_hessian":[7.2E1],"tree_param":{"num_deleted":"0","num_feature":"4","num_nodes":"1","size_leaf_vector":"0"}},{"base_weights":[4.5188283E-8],"default_left":[false],"id":48,"leaf_child_counts":[0],"left_children":[-1],"loss_changes":[8.906456E-7],"parents":[2147483647],"right_children":[-1],"split_conditions":[1.3556486E-8],"split_indices":[0],"sum_hessian":[7.2E1],"tree_param":{"num_deleted":"0","num_feature":"4","num_nodes":"1","size_leaf_vector":"0"}},{"base_weights":[4.1156802E-8],"default_left":[false],"id":49,"leaf_child_counts":[0],"left_children":[-1],"loss_changes":[8.9063474E-7],"parents":[2147483647],"right_children":[-1],"split_conditions":[1.2347042E-8],"split_indices":[0],"sum_hessian":[7.2E1],"tree_param":{"num_deleted":"0","num_feature":"4","num_nodes":"1","size_leaf_vector":"0"}},{"base_weights":[3.7227387E-8],"default_left":[false],"id":50,"leaf_child_counts":[0],"left_children":[-1],"loss_changes":[8.9062075E-7],"parents":[2147483647],"right_children":[-1],"split_conditions":[1.1168217E-8],"split_indices":[0],"sum_hessian":[7.2E1],"tree_param":{"num_deleted":"0","num_feature":"4","num_nodes":"1","size_leaf_vector":"0"}},{"base_weights":[3.4471693E-8],"default_left":[false],"id":51,"leaf_child_counts":[0],"left_children":[-1],"loss_changes":[8.9060245E-7],"parents":[2147483647],"right_children":[-1],"split_conditions":[1.0341508E-8],"split_indices":[0],"sum_hessian":[7.2E1],"tree_param":{"num_deleted":"0","num_feature":"4","num_nodes":"1","size_leaf_vector":"0"}},{"base_weights":[3.1894608E-8],"default_left":[false],"id":52,"leaf_child_counts":[0],"left_children":[-1],"loss_changes":[8.9058756E-7],"parents":[2147483647],"right_children":[-1],"split_conditions":[9.5683825E-9],"split_indices":[0],"sum_hessian":[7.2E1],"tree_param":{"num_deleted":"0","num_feature":"4","num_nodes":"1","size_leaf_vector":"0"}},{"base_weights":[2.9470618E-8],"default_left":[false],"id":53,"leaf_child_counts":[0],"left_children":[-1],"loss_changes":[8.9057505E-7],"parents":[2147483647],"right_children":[-1],"split_conditions":[8.841186E-9],"split_indices":[0],"sum_hessian":[7.2E1],"tree_param":{"num_deleted":"0","num_feature":"4","num_nodes":"1","size_leaf_vector":"0"}},{"base_weights":[2.7072144E-8],"default_left":[false],"id":54,"leaf_child_counts":[0],"left_children":[-1],"loss_changes":[8.905601E-7],"parents":[2147483647],"right_children":[-1],"split_conditions":[8.121644E-9],"split_indices":[0],"sum_hessian":[7.2E1],"tree_param":{"num_deleted":"0","num_feature":"4","num_nodes":"1","size_leaf_vector":"0"}},{"base_weights":[2.4852278E-8],"default_left":[false],"id":55,"leaf_child_counts":[0],"left_children":[-1],"loss_changes":[8.90552E-7],"parents":[2147483647],"right_children":[-1],"split_conditions":[7.455684E-9],"split_indices":[0],"sum_hessian":[7.2E1],"tree_param":{"num_deleted":"0","num_feature":"4","num_nodes":"1","size_leaf_vector":"0"}},{"base_weights":[2.2708962E-8],"default_left":[false],"id":56,"leaf_child_counts":[0],"left_children":[-1],"loss_changes":[8.9054333E-7],"parents":[2147483647],"right_children":[-1],"split_conditions":[6.8126886E-9],"split_indices":[0],"sum_hessian":[7.2E1],"tree_param":{"num_deleted":"0","num_feature":"4","num_nodes":"1","size_leaf_vector":"0"}},{"base_weights":[2.064219E-8],"default_left":[false],"id":57,"leaf_child_counts":[0],"left_children":[-1],"loss_changes":[8.905342E-7],"parents":[2147483647],"right_children":[-1],"split_conditions":[6.1926575E-9],"split_indices":[0],"sum_hessian":[7.2E1],"tree_param":{"num_deleted":"0","num_feature":"4","num_nodes":"1","size_leaf_vector":"0"}},{"base_weights":[1.875403E-8],"default_left":[false],"id":58,"leaf_child_counts":[0],"left_children":[-1],"loss_changes":[8.905319E-7],"parents":[2147483647],"right_children":[-1],"split_conditions":[5.6262093E-9],"split_indices":[0],"sum_hessian":[7.2E1],"tree_param":{"num_deleted":"0","num_feature":"4","num_nodes":"1","size_leaf_vector":"0"}},{"base_weights":[1.6891384E-8],"default_left":[false],"id":59,"leaf_child_counts":[0],"left_children":[-1],"loss_changes":[8.9052713E-7],"parents":[2147483647],"right_children":[-1],"split_conditions":[5.0674154E-9],"split_indices":[0],"sum_hessian":[7.2E1],"tree_param":{"num_deleted":"0","num_feature":"4","num_nodes":"1","size_leaf_vector":"0"}},{"base_weights":[1.5105286E-8],"default_left":[false],"id":60,"leaf_child_counts":[0],"left_children":[-1],"loss_changes":[8.9052185E-7],"parents":[2147483647],"right_children":[-1],"split_conditions":[4.5315858E-9],"split_indices":[0],"sum_hessian":[7.2E1],"tree_param":{"num_deleted":"0","num_feature":"4","num_nodes":"1","size_leaf_vector":"0"}},{"base_weights":[1.3446767E-8],"default_left":[false],"id":61,"leaf_child_counts":[0],"left_children":[-1],"loss_changes":[8.905215E-7],"parents":[2147483647],"right_children":[-1],"split_conditions":[4.0340304E-9],"split_indices":[0],"sum_hessian":[7.2E1],"tree_param":{"num_deleted":"0","num_feature":"4","num_nodes":"1","size_leaf_vector":"0"}},{"base_weights":[1.18647945E-8],"default_left":[false],"id":62,"leaf_child_counts":[0],"left_children":[-1],"loss_changes":[8.905206E-7],"parents":[2147483647],"right_children":[-1],"split_conditions":[3.5594385E-9],"split_indices":[0],"sum_hessian":[7.2E1],"tree_param":{"num_deleted":"0","num_feature":"4","num_nodes":"1","size_leaf_vector":"0"}},{"base_weights":[1.130345E-8],"default_left":[false],"id":63,"leaf_child_counts":[0],"left_children":[-1],"loss_changes":[8.9051287E-7],"parents":[2147483647],"right_children":[-1],"split_conditions":[3.391035E-9],"split_indices":[0],"sum_hessian":[7.2E1],"tree_param":{"num_deleted":"0","num_feature":"4","num_nodes":"1","size_leaf_vector":"0"}},{"base_weights":[1.0742104E-8],"default_left":[false],"id":64,"leaf_child_counts":[0],"left_children":[-1],"loss_changes":[8.905051E-7],"parents":[2147483647],"right_children":[-1],"split_conditions":[3.2226313E-9],"split_indices":[0],"sum_hessian":[7.2E1],"tree_param":{"num_deleted":"0","num_feature":"4","num_nodes":"1","size_leaf_vector":"0"}},{"base_weights":[1.0257306E-8],"default_left":[false],"id":65,"leaf_child_counts":[0],"left_children":[-1],"loss_changes":[8.9049684E-7],"parents":[2147483647],"right_children":[-1],"split_conditions":[3.077192E-9],"split_indices":[0],"sum_hessian":[7.2E1],"tree_param":{"num_deleted":"0","num_feature":"4","num_nodes":"1","size_leaf_vector":"0"}},{"base_weights":[9.772508E-9],"default_left":[false],"id":66,"leaf_child_counts":[0],"left_children":[-1],"loss_changes":[8.904886E-7],"parents":[2147483647],"right_children":[-1],"split_conditions":[2.9317526E-9],"split_indices":[0],"sum_hessian":[7.2E1],"tree_param":{"num_deleted":"0","num_feature":"4","num_nodes":"1","size_leaf_vector":"0"}},{"base_weights":[9.28771E-9],"default_left":[false],"id":67,"leaf_child_counts":[0],"left_children":[-1],"loss_changes":[8.9048035E-7],"parents":[2147483647],"right_children":[-1],"split_conditions":[2.7863132E-9],"split_indices":[0],"sum_hessian":[7.2E1],"tree_param":{"num_deleted":"0","num_feature":"4","num_nodes":"1","size_leaf_vector":"0"}},{"base_weights":[8.879459E-9],"default_left":[false],"id":68,"leaf_child_counts":[0],"left_children":[-1],"loss_changes":[8.9047506E-7],"parents":[2147483647],"right_children":[-1],"split_conditions":[2.6638378E-9],"split_indices":[0],"sum_hessian":[7.2E1],"tree_param":{"num_deleted":"0","num_feature":"4","num_nodes":"1","size_leaf_vector":"0"}},{"base_weights":[8.573271E-9],"default_left":[false],"id":69,"leaf_child_counts":[0],"left_children":[-1],"loss_changes":[8.9047364E-7],"parents":[2147483647],"right_children":[-1],"split_conditions":[2.5719813E-9],"split_indices":[0],"sum_hessian":[7.2E1],"tree_param":{"num_deleted":"0","num_feature":"4","num_nodes":"1","size_leaf_vector":"0"}},{"base_weights":[8.216051E-9],"default_left":[false],"id":70,"leaf_child_counts":[0],"left_children":[-1],"loss_changes":[8.904703E-7],"parents":[2147483647],"right_children":[-1],"split_conditions":[2.4648155E-9],"split_indices":[0],"sum_hessian":[7.2E1],"tree_param":{"num_deleted":"0","num_feature":"4","num_nodes":"1","size_leaf_vector":"0"}},{"base_weights":[7.858832E-9],"default_left":[false],"id":71,"leaf_child_counts":[0],"left_children":[-1],"loss_changes":[8.9046694E-7],"parents":[2147483647],"right_children":[-1],"split_conditions":[2.3576496E-9],"split_indices":[0],"sum_hessian":[7.2E1],"tree_param":{"num_deleted":"0","num_feature":"4","num_nodes":"1","size_leaf_vector":"0"}},{"base_weights":[7.450581E-9],"default_left":[false],"id":72,"leaf_child_counts":[0],"left_children":[-1],"loss_changes":[8.9046165E-7],"parents":[2147483647],"right_children":[-1],"split_conditions":[2.2351743E-9],"split_indices":[0],"sum_hessian":[7.2E1],"tree_param":{"num_deleted":"0","num_feature":"4","num_nodes":"1","size_leaf_vector":"0"}},{"base_weights":[7.2209394E-9],"default_left":[false],"id":73,"leaf_child_counts":[0],"left_children":[-1],"loss_changes":[8.904597E-7],"parents":[2147483647],"right_children":[-1],"split_conditions":[2.1662818E-9],"split_indices":[0],"sum_hessian":[7.2E1],"tree_param":{"num_deleted":"0","num_feature":"4","num_nodes":"1","size_leaf_vector":"0"}},{"base_weights":[6.940267E-9],"default_left":[false],"id":74,"leaf_child_counts":[0],"left_children":[-1],"loss_changes":[8.9045585E-7],"parents":[2147483647],"right_children":[-1],"split_conditions":[2.0820803E-9],"split_indices":[0],"sum_hessian":[7.2E1],"tree_param":{"num_deleted":"0","num_feature":"4","num_nodes":"1","size_leaf_vector":"0"}},{"base_weights":[6.659594E-9],"default_left":[false],"id":75,"leaf_child_counts":[0],"left_children":[-1],"loss_changes":[8.90452E-7],"parents":[2147483647],"right_children":[-1],"split_conditions":[1.9978783E-9],"split_indices":[0],"sum_hessian":[7.2E1],"tree_param":{"num_deleted":"0","num_feature":"4","num_nodes":"1","size_leaf_vector":"0"}},{"base_weights":[6.32789E-9],"default_left":[false],"id":76,"leaf_child_counts":[0],"left_children":[-1],"loss_changes":[8.904462E-7],"parents":[2147483647],"right_children":[-1],"split_conditions":[1.8983672E-9],"split_indices":[0],"sum_hessian":[7.2E1],"tree_param":{"num_deleted":"0","num_feature":"4","num_nodes":"1","size_leaf_vector":"0"}},{"base_weights":[6.098249E-9],"default_left":[false],"id":77,"leaf_child_counts":[0],"left_children":[-1],"loss_changes":[8.9044426E-7],"parents":[2147483647],"right_children":[-1],"split_conditions":[1.8294748E-9],"split_indices":[0],"sum_hessian":[7.2E1],"tree_param":{"num_deleted":"0","num_feature":"4","num_nodes":"1","size_leaf_vector":"0"}},{"base_weights":[5.8175766E-9],"default_left":[false],"id":78,"leaf_child_counts":[0],"left_children":[-1],"loss_changes":[8.904404E-7],"parents":[2147483647],"right_children":[-1],"split_conditions":[1.745273E-9],"split_indices":[0],"sum_hessian":[7.2E1],"tree_param":{"num_deleted":"0","num_feature":"4","num_nodes":"1","size_leaf_vector":"0"}},{"base_weights":[5.5369043E-9],"default_left":[false],"id":79,"leaf_child_counts":[0],"left_children":[-1],"loss_changes":[8.904365E-7],"parents":[2147483647],"right_children":[-1],"split_conditions":[1.6610714E-9],"split_indices":[0],"sum_hessian":[7.2E1],"tree_param":{"num_deleted":"0","num_feature":"4","num_nodes":"1","size_leaf_vector":"0"}},{"base_weights":[5.2052003E-9],"default_left":[false],"id":80,"leaf_child_counts":[0],"left_children":[-1],"loss_changes":[8.904307E-7],"parents":[2147483647],"right_children":[-1],"split_conditions":[1.5615601E-9],"split_indices":[0],"sum_hessian":[7.2E1],"tree_param":{"num_deleted":"0","num_feature":"4","num_nodes":"1","size_leaf_vector":"0"}},{"base_weights":[4.975559E-9],"default_left":[false],"id":81,"leaf_child_counts":[0],"left_children":[-1],"loss_changes":[8.904288E-7],"parents":[2147483647],"right_children":[-1],"split_conditions":[1.4926678E-9],"split_indices":[0],"sum_hessian":[7.2E1],"tree_param":{"num_deleted":"0","num_feature":"4","num_nodes":"1","size_leaf_vector":"0"}},{"base_weights":[4.6948863E-9],"default_left":[false],"id":82,"leaf_child_counts":[0],"left_children":[-1],"loss_changes":[8.90425E-7],"parents":[2147483647],"right_children":[-1],"split_conditions":[1.4084659E-9],"split_indices":[0],"sum_hessian":[7.2E1],"tree_param":{"num_deleted":"0","num_feature":"4","num_nodes":"1","size_leaf_vector":"0"}},{"base_weights":[4.414214E-9],"default_left":[false],"id":83,"leaf_child_counts":[0],"left_children":[-1],"loss_changes":[8.904211E-7],"parents":[2147483647],"right_children":[-1],"split_conditions":[1.3242643E-9],"split_indices":[0],"sum_hessian":[7.2E1],"tree_param":{"num_deleted":"0","num_feature":"4","num_nodes":"1","size_leaf_vector":"0"}},{"base_weights":[4.159057E-9],"default_left":[false],"id":84,"leaf_child_counts":[0],"left_children":[-1],"loss_changes":[8.9041475E-7],"parents":[2147483647],"right_children":[-1],"split_conditions":[1.2477172E-9],"split_indices":[0],"sum_hessian":[7.2E1],"tree_param":{"num_deleted":"0","num_feature":"4","num_nodes":"1","size_leaf_vector":"0"}},{"base_weights":[4.0059627E-9],"default_left":[false],"id":85,"leaf_child_counts":[0],"left_children":[-1],"loss_changes":[8.9041237E-7],"parents":[2147483647],"right_children":[-1],"split_conditions":[1.2017889E-9],"split_indices":[0],"sum_hessian":[7.2E1],"tree_param":{"num_deleted":"0","num_feature":"4","num_nodes":"1","size_leaf_vector":"0"}},{"base_weights":[3.8018375E-9],"default_left":[false],"id":86,"leaf_child_counts":[0],"left_children":[-1],"loss_changes":[8.9040793E-7],"parents":[2147483647],"right_children":[-1],"split_conditions":[1.1405513E-9],"split_indices":[0],"sum_hessian":[7.2E1],"tree_param":{"num_deleted":"0","num_feature":"4","num_nodes":"1","size_leaf_vector":"0"}},{"base_weights":[3.597712E-9],"default_left":[false],"id":87,"leaf_child_counts":[0],"left_children":[-1],"loss_changes":[8.904036E-7],"parents":[2147483647],"right_children":[-1],"split_conditions":[1.0793136E-9],"split_indices":[0],"sum_hessian":[7.2E1],"tree_param":{"num_deleted":"0","num_feature":"4","num_nodes":"1","size_leaf_vector":"0"}},{"base_weights":[3.342555E-9],"default_left":[false],"id":88,"leaf_child_counts":[0],"left_children":[-1],"loss_changes":[8.9039725E-7],"parents":[2147483647],"right_children":[-1],"split_conditions":[1.0027665E-9],"split_indices":[0],"sum_hessian":[7.2E1],"tree_param":{"num_deleted":"0","num_feature":"4","num_nodes":"1","size_leaf_vector":"0"}},{"base_weights":[3.189461E-9],"default_left":[false],"id":89,"leaf_child_counts":[0],"left_children":[-1],"loss_changes":[8.9039486E-7],"parents":[2147483647],"right_children":[-1],"split_conditions":[9.568383E-10],"split_indices":[0],"sum_hessian":[7.2E1],"tree_param":{"num_deleted":"0","num_feature":"4","num_nodes":"1","size_leaf_vector":"0"}},{"base_weights":[2.9853353E-9],"default_left":[false],"id":90,"leaf_child_counts":[0],"left_children":[-1],"loss_changes":[8.903904E-7],"parents":[2147483647],"right_children":[-1],"split_conditions":[8.9560065E-10],"split_indices":[0],"sum_hessian":[7.2E1],"tree_param":{"num_deleted":"0","num_feature":"4","num_nodes":"1","size_leaf_vector":"0"}},{"base_weights":[2.9087883E-9],"default_left":[false],"id":91,"leaf_child_counts":[0],"left_children":[-1],"loss_changes":[8.90391E-7],"parents":[2147483647],"right_children":[-1],"split_conditions":[8.726365E-10],"split_indices":[0],"sum_hessian":[7.2E1],"tree_param":{"num_deleted":"0","num_feature":"4","num_nodes":"1","size_leaf_vector":"0"}},{"base_weights":[2.8322413E-9],"default_left":[false],"id":92,"leaf_child_counts":[0],"left_children":[-1],"loss_changes":[8.9039145E-7],"parents":[2147483647],"right_children":[-1],"split_conditions":[8.4967244E-10],"split_indices":[0],"sum_hessian":[7.2E1],"tree_param":{"num_deleted":"0","num_feature":"4","num_nodes":"1","size_leaf_vector":"0"}},{"base_weights":[2.7556941E-9],"default_left":[false],"id":93,"leaf_child_counts":[0],"left_children":[-1],"loss_changes":[8.90392E-7],"parents":[2147483647],"right_children":[-1],"split_conditions":[8.2670826E-10],"split_indices":[0],"sum_hessian":[7.2E1],"tree_param":{"num_deleted":"0","num_feature":"4","num_nodes":"1","size_leaf_vector":"0"}},{"base_weights":[2.6791471E-9],"default_left":[false],"id":94,"leaf_child_counts":[0],"left_children":[-1],"loss_changes":[8.9039247E-7],"parents":[2147483647],"right_children":[-1],"split_conditions":[8.037442E-10],"split_indices":[0],"sum_hessian":[7.2E1],"tree_param":{"num_deleted":"0","num_feature":"4","num_nodes":"1","size_leaf_vector":"0"}},{"base_weights":[2.6026001E-9],"default_left":[false],"id":95,"leaf_child_counts":[0],"left_children":[-1],"loss_changes":[8.9039304E-7],"parents":[2147483647],"right_children":[-1],"split_conditions":[7.8078005E-10],"split_indices":[0],"sum_hessian":[7.2E1],"tree_param":{"num_deleted":"0","num_feature":"4","num_nodes":"1","size_leaf_vector":"0"}},{"base_weights":[2.526053E-9],"default_left":[false],"id":96,"leaf_child_counts":[0],"left_children":[-1],"loss_changes":[8.903935E-7],"parents":[2147483647],"right_children":[-1],"split_conditions":[7.578159E-10],"split_indices":[0],"sum_hessian":[7.2E1],"tree_param":{"num_deleted":"0","num_feature":"4","num_nodes":"1","size_leaf_vector":"0"}},{"base_weights":[2.449506E-9],"default_left":[false],"id":97,"leaf_child_counts":[0],"left_children":[-1],"loss_changes":[8.9039406E-7],"parents":[2147483647],"right_children":[-1],"split_conditions":[7.348518E-10],"split_indices":[0],"sum_hessian":[7.2E1],"tree_param":{"num_deleted":"0","num_feature":"4","num_nodes":"1","size_leaf_vector":"0"}},{"base_weights":[2.372959E-9],"default_left":[false],"id":98,"leaf_child_counts":[0],"left_children":[-1],"loss_changes":[8.903945E-7],"parents":[2147483647],"right_children":[-1],"split_conditions":[7.118877E-10],"split_indices":[0],"sum_hessian":[7.2E1],"tree_param":{"num_deleted":"0","num_feature":"4","num_nodes":"1","size_leaf_vector":"0"}},{"base_weights":[2.2964117E-9],"default_left":[false],"id":99,"leaf_child_counts":[0],"left_children":[-1],"loss_changes":[8.903951E-7],"parents":[2147483647],"right_children":[-1],"split_conditions":[6.8892353E-10],"split_indices":[0],"sum_hessian":[7.2E1],"tree_param":{"num_deleted":"0","num_feature":"4","num_nodes":"1","size_leaf_vector":"0"}}]},"name":"gbtree"},"learner_model_param":{"base_score":"5E-1","num_class":"0","num_feature":"4"},"objective":{"name":"reg:squarederror","reg_loss_param":{"scale_pos_weight":"1"}}},"version":[1,2,0]}