{"learner":{"attributes":{"scikit_learn":"{\"n_estimators\": 100, \"objective\": \"reg:squarederror\", \"max_depth\": null, \"learning_rate\": null, \"verbosity\": null, \"booster\": null, \"tree_method\": null, \"gamma\": null, \"min_child_weight\": null, \"max_delta_step\": null, \"subsample\": null, \"colsample_bytree\": null, \"colsample_bylevel\": null, \"colsample_bynode\": null, \"reg_alpha\": null, \"reg_lambda\": null, \"scale_pos_weight\": null, \"base_score\": null, \"missing\": NaN, \"num_parallel_tree\": null, \"kwargs\": {}, \"random_state\": 42, \"n_jobs\": null, \"monotone_constraints\": null, \"interaction_constraints\": null, \"importance_type\": \"gain\", \"gpu_id\": null, \"validate_parameters\": null, \"n_features_in_\": 2, \"type\": \"XGBRegressor\"}"},"gradient_booster":{"model":{"gbtree_model_param":{"num_trees":"100","size_leaf_vector":"0"},"tree_info":[0,0,0,0,0,0,0,0,0,0,0,0,0,0,0,0,0,0,0,0,0,0,0,0,0,0,0,0,0,0,0,0,0,0,0,0,0,0,0,0,0,0,0,0,0,0,0,0,0,0,0,0,0,0,0,0,0,0,0,0,0,0,0,0,0,0,0,0,0,0,0,0,0,0,0,0,0,0,0,0,0,0,0,0,0,0,0,0,0,0,0,0,0,0,0,0,0,0,0,0],"trees":[{"base_weights":[-2.2284329E-1,-3.9964285E-1,2.5145945E-1,-4.48971E-1,-2.7286667E-1],"default_left":[true,true,false,false,false],"id":0,"leaf_child_counts":[0,0,0,0,0],"left_children":[1,3,-1,-1,-1],"loss_changes":[1.1337269E1,4.9034786E-1,0E0,0E0,0E0],"parents":[2147483647,0,0,1,1],"right_children":[2,4,-1,-1,-1],"split_conditions":[5.5463635E2,5.1251337E2,7.543784E-2,-1.3469131E-1,-8.1860006E-2],"split_indices":[0,0,0,0,0],"sum_hessian":[1.33E2,9.7E1,3.6E1,6.8E1,2.9E1],"tree_param":{"num_deleted":"0","num_feature":"2","num_nodes":"5","size_leaf_vector":"0"}},{"base_weights":[-1.5704338E-1,-2.819597E-1,1.7806047E-1,-3.1623176E-1,-1.9373533E-1],"default_left":[true,true,false,false,false],"id":1,"leaf_child_counts":[0,0,0,0,0],"left_children":[1,3,-1,-1,-1],"loss_changes":[5.6594377E0,2.3505116E-1,0E0,0E0,0E0],"parents":[2147483647,0,0,1,1],"right_children":[2,4,-1,-1,-1],"split_conditions":[5.5463635E2,5.1251337E2,5.3418145E-2,-9.486953E-2,-5.81206E-2],"split_indices":[0,0,0,0,0],"sum_hessian":[1.33E2,9.7E1,3.6E1,6.8E1,2.9E1],"tree_param":{"num_deleted":"0","num_feature":"2","num_nodes":"5","size_leaf_vector":"0"}},{"base_weights":[-1.1067345E-1,-1.9893292E-1,1.2608606E-1,-2.2273716E-1,-1.3755207E-1],"default_left":[true,true,false,false,false],"id":2,"leaf_child_counts":[0,0,0,0,0],"left_children":[1,3,-1,-1,-1],"loss_changes":[2.8251824E0,1.12552404E-1,0E0,0E0,0E0],"parents":[2147483647,0,0,1,1],"right_children":[2,4,-1,-1,-1],"split_conditions":[5.5463635E2,5.1251337E2,3.782582E-2,-6.682115E-2,-4.126562E-2],"split_indices":[0,0,0,0,0],"sum_hessian":[1.33E2,9.7E1,3.6E1,6.8E1,2.9E1],"tree_param":{"num_deleted":"0","num_feature":"2","num_nodes":"5","size_leaf_vector":"0"}},{"base_weights":[-7.7995755E-2,-1.4035597E-1,8.928255E-2,-1.780453E-1,-1.1659134E-1,-1.2986454E-1,-9.766199E-2],"default_left":[true,true,false,false,true,false,false],"id":3,"leaf_child_counts":[0,0,0,0,0,0,0],"left_children":[1,3,-1,-1,5,-1,-1],"loss_changes":[1.4103539E0,6.7017436E-2,0E0,0E0,3.146112E-3,0E0,0E0],"parents":[2147483647,0,0,1,1,4,4],"right_children":[2,4,-1,-1,6,-1,-1],"split_conditions":[5.5463635E2,4.849944E2,2.6784766E-2,-5.3413592E-2,5.1251337E2,-3.8959365E-2,-2.9298598E-2],"split_indices":[0,0,0,0,0,0,0],"sum_hessian":[1.33E2,9.7E1,3.6E1,3.5E1,6.2E1,3.3E1,2.9E1],"tree_param":{"num_deleted":"0","num_feature":"2","num_nodes":"7","size_leaf_vector":"0"}},{"base_weights":[-5.5305135E-2,-9.949072E-2,6.322168E-2,-1.2611541E-1,-8.269739E-2,-9.2051044E-2,-6.9340006E-2],"default_left":[true,true,false,false,true,false,false],"id":4,"leaf_child_counts":[0,0,0,0,0,0,0],"left_children":[1,3,-1,-1,5,-1,-1],"loss_changes":[7.080716E-1,3.338808E-2,0E0,0E0,1.4884472E-3,0E0,0E0],"parents":[2147483647,0,0,1,1,4,4],"right_children":[2,4,-1,-1,6,-1,-1],"split_conditions":[5.5463635E2,4.849944E2,1.8966503E-2,-3.7834626E-2,5.1251337E2,-2.7615314E-2,-2.0802002E-2],"split_indices":[0,0,0,0,0,0,0],"sum_hessian":[1.33E2,9.7E1,3.6E1,3.5E1,6.2E1,3.3E1,2.9E1],"tree_param":{"num_deleted":"0","num_feature":"2","num_nodes":"7","size_leaf_vector":"0"}},{"base_weights":[-3.9215725E-2,-7.052363E-2,4.4767793E-2,-8.933174E-2,-5.8656707E-2,-6.524795E-2,-4.923141E-2],"default_left":[true,true,false,false,true,false,false],"id":5,"leaf_child_counts":[0,0,0,0,0,0,0],"left_children":[1,3,-1,-1,5,-1,-1],"loss_changes":[3.554898E-1,1.6633123E-2,0E0,0E0,7.015914E-4,0E0,0E0],"parents":[2147483647,0,0,1,1,4,4],"right_children":[2,4,-1,-1,6,-1,-1],"split_conditions":[5.5463635E2,4.849944E2,1.3430338E-2,-2.6799522E-2,5.1251337E2,-1.9574387E-2,-1.4769424E-2],"split_indices":[0,0,0,0,0,0,0],"sum_hessian":[1.33E2,9.7E1,3.6E1,3.5E1,6.2E1,3.3E1,2.9E1],"tree_param":{"num_deleted":"0","num_feature":"2","num_nodes":"7","size_leaf_vector":"0"}},{"base_weights":[-2.7807076E-2,-4.9990445E-2,3.1700417E-2,-6.327665E-2,-4.1604828E-2,-6.9178775E-2,-4.101324E-2,-4.6249278E-2,-3.495429E-2],"default_left":[true,true,false,true,true,false,false,false,false],"id":6,"leaf_child_counts":[0,0,0,0,0,0,0,0,0],"left_children":[1,3,-1,5,7,-1,-1,-1,-1],"loss_changes":[1.7847499E-1,8.28588E-3,0E0,1.8932074E-3,3.29338E-4,0E0,0E0,0E0,0E0],"parents":[2147483647,0,0,1,1,3,3,4,4],"right_children":[2,4,-1,6,8,-1,-1,-1,-1],"split_conditions":[5.5463635E2,4.849944E2,9.510126E-3,5.167213E2,5.1251337E2,-2.0753633E-2,-1.2303973E-2,-1.3874784E-2,-1.0486288E-2],"split_indices":[0,0,0,1,0,0,0,0,0],"sum_hessian":[1.33E2,9.7E1,3.6E1,3.5E1,6.2E1,2.6E1,9E0,3.3E1,2.9E1],"tree_param":{"num_deleted":"0","num_feature":"2","num_nodes":"9","size_leaf_vector":"0"}},{"base_weights":[-1.982247E-2,-3.5579216E-2,2.2447353E-2,-4.5211926E-2,-2.9510062E-2,-4.91938E-2,-2.9939666E-2,-3.2782577E-2,-2.4817545E-2],"default_left":[true,true,false,true,true,false,false,false,false],"id":7,"leaf_child_counts":[0,0,0,0,0,0,0,0,0],"left_children":[1,3,-1,5,7,-1,-1,-1,-1],"loss_changes":[9.004733E-2,4.395105E-3,0E0,7.163957E-4,1.5386567E-4,0E0,0E0,0E0,0E0],"parents":[2147483647,0,0,1,1,3,3,4,4],"right_children":[2,4,-1,6,8,-1,-1,-1,-1],"split_conditions":[5.5463635E2,4.849944E2,6.7342063E-3,5.167213E2,5.1251337E2,-1.4758141E-2,-8.9819E-3,-9.834774E-3,-7.4452637E-3],"split_indices":[0,0,0,1,0,0,0,0,0],"sum_hessian":[1.33E2,9.7E1,3.6E1,3.5E1,6.2E1,2.6E1,9E0,3.3E1,2.9E1],"tree_param":{"num_deleted":"0","num_feature":"2","num_nodes":"9","size_leaf_vector":"0"}},{"base_weights":[-1.41315935E-2,-2.5324024E-2,1.589516E-2,-3.2307792E-2,-2.0931331E-2,-3.4982257E-2,-2.185596E-2,-2.323706E-2,-1.7620461E-2],"default_left":[true,true,false,true,true,false,false,false,false],"id":8,"leaf_child_counts":[0,0,0,0,0,0,0,0,0],"left_children":[1,3,-1,5,7,-1,-1,-1,-1],"loss_changes":[4.5436233E-2,2.3301616E-3,0E0,2.4173781E-4,7.149018E-5,0E0,0E0,0E0,0E0],"parents":[2147483647,0,0,1,1,3,3,4,4],"right_children":[2,4,-1,6,8,-1,-1,-1,-1],"split_conditions":[5.5463635E2,4.849944E2,4.768548E-3,5.167213E2,5.1251337E2,-1.0494677E-2,-6.556788E-3,-6.9711185E-3,-5.2861385E-3],"split_indices":[0,0,0,1,0,0,0,0,0],"sum_hessian":[1.33E2,9.7E1,3.6E1,3.5E1,6.2E1,2.6E1,9E0,3.3E1,2.9E1],"tree_param":{"num_deleted":"0","num_feature":"2","num_nodes":"9","size_leaf_vector":"0"}},{"base_weights":[-1.0075247E-2,-1.8025883E-2,1.1255496E-2,-2.3089107E-2,-1.4846487E-2,-2.487627E-2,-1.5954852E-2,-1.6470972E-2,-1.25105195E-2],"default_left":[true,true,false,true,true,false,false,false,false],"id":9,"leaf_child_counts":[0,0,0,0,0,0,0,0,0],"left_children":[1,3,-1,5,7,-1,-1,-1,-1],"loss_changes":[2.292835E-2,1.2348108E-3,0E0,6.210618E-5,3.3008866E-5,0E0,0E0,0E0,0E0],"parents":[2147483647,0,0,1,1,3,3,4,4],"right_children":[2,4,-1,6,8,-1,-1,-1,-1],"split_conditions":[5.5463635E2,4.849944E2,3.376649E-3,5.167213E2,5.1251337E2,-7.4628815E-3,-4.786456E-3,-4.941292E-3,-3.753156E-3],"split_indices":[0,0,0,1,0,0,0,0,0],"sum_hessian":[1.33E2,9.7E1,3.6E1,3.5E1,6.2E1,2.6E1,9E0,3.3E1,2.9E1],"tree_param":{"num_deleted":"0","num_feature":"2","num_nodes":"9","size_leaf_vector":"0"}},{"base_weights":[-7.1837767E-3,-1.283183E-2,7.970088E-3,-1.6502634E-2,-1.0530548E-2,-1.7689792E-2,-1.1647043E-2,-1.1675013E-2,-8.8824695E-3],"default_left":[true,true,false,true,true,false,false,false,false],"id":10,"leaf_child_counts":[0,0,0,0,0,0,0,0,0],"left_children":[1,3,-1,5,7,-1,-1,-1,-1],"loss_changes":[1.1571308E-2,6.54079E-4,0E0,1.4826655E-6,1.5125144E-5,0E0,0E0,0E0,0E0],"parents":[2147483647,0,0,1,1,3,3,4,4],"right_children":[2,4,-1,6,8,-1,-1,-1,-1],"split_conditions":[5.5463635E2,4.849944E2,2.3910266E-3,5.167213E2,5.1251337E2,-5.3069377E-3,-3.494113E-3,-3.5025042E-3,-2.664741E-3],"split_indices":[0,0,0,1,0,0,0,0,0],"sum_hessian":[1.33E2,9.7E1,3.6E1,3.5E1,6.2E1,2.6E1,9E0,3.3E1,2.9E1],"tree_param":{"num_deleted":"0","num_feature":"2","num_nodes":"9","size_leaf_vector":"0"}},{"base_weights":[-5.1225075E-3,-9.135019E-3,5.6436704E-3,-1.1796318E-2,-7.469276E-3,-8.275525E-3,-6.306552E-3],"default_left":[true,true,false,false,true,false,false],"id":11,"leaf_child_counts":[0,0,0,0,0,0,0],"left_children":[1,3,-1,-1,5,-1,-1],"loss_changes":[5.8402754E-3,3.4632813E-4,0E0,0E0,6.8692025E-6,0E0,0E0],"parents":[2147483647,0,0,1,1,4,4],"right_children":[2,4,-1,-1,6,-1,-1],"split_conditions":[5.5463635E2,4.849944E2,1.6931013E-3,-3.5388956E-3,5.1251337E2,-2.4826576E-3,-1.8919656E-3],"split_indices":[0,0,0,0,0,0,0],"sum_hessian":[1.33E2,9.7E1,3.6E1,3.5E1,6.2E1,3.3E1,2.9E1],"tree_param":{"num_deleted":"0","num_feature":"2","num_nodes":"7","size_leaf_vector":"0"}},{"base_weights":[-3.6321804E-3,-6.475261E-3,3.996308E-3,-1.3691329E-2,-6.1032656E-3,-6.7497096E-3,-4.4776467E-3],"default_left":[true,true,false,false,true,false,false],"id":12,"leaf_child_counts":[0,0,0,0,0,0,0],"left_children":[1,3,-1,-1,5,-1,-1],"loss_changes":[2.9321234E-3,1.7950358E-4,0E0,0E0,6.9610076E-5,0E0,0E0],"parents":[2147483647,0,0,1,1,4,4],"right_children":[2,4,-1,-1,6,-1,-1],"split_conditions":[5.5463635E2,4.6040808E2,1.1988925E-3,-4.107399E-3,5.1251337E2,-2.024913E-3,-1.343294E-3],"split_indices":[0,0,0,0,0,0,0],"sum_hessian":[1.33E2,9.7E1,3.6E1,3E0,9.4E1,6.5E1,2.9E1],"tree_param":{"num_deleted":"0","num_feature":"2","num_nodes":"7","size_leaf_vector":"0"}},{"base_weights":[-2.5893683E-3,-4.608965E-3,2.829816E-3,-6.2135193E-3,-3.6189184E-3,-1.061078E-2,-5.4922295E-3,-3.494914E-3,-6.0956012E-3],"default_left":[true,true,false,true,false,false,true,false,false],"id":13,"leaf_child_counts":[0,0,0,0,0,0,0,0,0],"left_children":[1,3,-1,5,-1,-1,7,-1,-1],"loss_changes":[1.4796142E-3,1.3319496E-4,0E0,5.5904384E-5,0E0,0E0,1.846545E-5,0E0,0E0],"parents":[2147483647,0,0,1,1,3,3,6,6],"right_children":[2,4,-1,6,-1,-1,8,-1,-1],"split_conditions":[5.5463635E2,4.849944E2,8.489448E-4,4.6040808E2,-1.0856756E-3,-3.183234E-3,4.641494E2,-1.0484742E-3,-1.8286804E-3],"split_indices":[0,0,0,0,0,0,0,0,0],"sum_hessian":[1.33E2,9.7E1,3.6E1,3.5E1,6.2E1,3E0,3.2E1,9E0,2.3E1],"tree_param":{"num_deleted":"0","num_feature":"2","num_nodes":"9","size_leaf_vector":"0"}},{"base_weights":[-1.859553E-3,-3.2991953E-3,2.0038115E-3,-8.223355E-3,-3.0571339E-3,-3.9317473E-3,-2.5504772E-3,-2.551286E-3,-4.3431167E-3,-2.8467844E-3,-2.1296465E-3],"default_left":[true,true,false,false,true,true,true,false,false,false,false],"id":14,"leaf_child_counts":[0,0,0,0,0,0,0,0,0,0,0],"left_children":[1,3,-1,-1,5,7,9,-1,-1,-1,-1],"loss_changes":[7.519006E-4,9.167113E-5,0E0,0E0,3.2069394E-5,7.659488E-6,1.7931452E-6,0E0,0E0,0E0,0E0],"parents":[2147483647,0,0,1,1,4,4,5,5,6,6],"right_children":[2,4,-1,-1,6,8,10,-1,-1,-1,-1],"split_conditions":[5.5463635E2,4.6040808E2,6.0114346E-4,-2.4670064E-3,4.849944E2,4.641494E2,5.1251337E2,-7.6538586E-4,-1.3029351E-3,-8.540354E-4,-6.38894E-4],"split_indices":[0,0,0,0,0,0,0,0,0,0,0],"sum_hessian":[1.33E2,9.7E1,3.6E1,3E0,9.4E1,3.2E1,6.2E1,9E0,2.3E1,3.3E1,2.9E1],"tree_param":{"num_deleted":"0","num_feature":"2","num_nodes":"11","size_leaf_vector":"0"}},{"base_weights":[-1.342197E-3,-2.370951E-3,1.4188869E-3,-6.3730995E-3,-2.1774822E-3,-2.814899E-3,-1.809034E-3,-1.862438E-3,-3.0944701E-3],"default_left":[true,true,false,false,true,true,false,false,false],"id":15,"leaf_child_counts":[0,0,0,0,0,0,0,0,0],"left_children":[1,3,-1,-1,5,7,-1,-1,-1],"loss_changes":[3.8398796E-4,6.200321E-5,0E0,0E0,1.721899E-5,3.0240044E-6,8.560164E-7,0E0,0E0],"parents":[2147483647,0,0,1,1,4,4,5,5],"right_children":[2,4,-1,-1,6,8,-1,-1,-1],"split_conditions":[5.5463635E2,4.6040808E2,4.256661E-4,-1.9119299E-3,4.849944E2,4.641494E2,-5.4271024E-4,-5.5873144E-4,-9.2834106E-4],"split_indices":[0,0,0,0,0,0,0,0,0],"sum_hessian":[1.33E2,9.7E1,3.6E1,3E0,9.4E1,3.2E1,6.2E1,9E0,2.3E1],"tree_param":{"num_deleted":"0","num_feature":"2","num_nodes":"9","size_leaf_vector":"0"}},{"base_weights":[-9.657666E-4,-1.6998863E-3,1.0047604E-3,-4.939152E-3,-1.5456026E-3,-1.7758989E-3,-9.874307E-4,-2.0154926E-3,-1.4911196E-3,-1.3595804E-3,-2.2048107E-3],"default_left":[true,true,false,false,true,true,false,true,false,false,false],"id":16,"leaf_child_counts":[0,0,0,0,0,0,0,0,0,0,0],"left_children":[1,3,-1,-1,5,7,-1,9,-1,-1,-1],"loss_changes":[1.9555273E-4,4.1343097E-5,0E0,0E0,1.04581995E-5,1.4979305E-6,0E0,1.100183E-6,0E0,0E0,0E0],"parents":[2147483647,0,0,1,1,4,4,5,5,7,7],"right_children":[2,4,-1,-1,6,8,-1,10,-1,-1,-1],"split_conditions":[5.5463635E2,4.6040808E2,3.0142814E-4,-1.4817456E-3,5.1251337E2,4.849944E2,-2.962292E-4,4.641494E2,-4.4733591E-4,-4.0787415E-4,-6.614432E-4],"split_indices":[0,0,0,0,0,0,0,0,0,0,0],"sum_hessian":[1.33E2,9.7E1,3.6E1,3E0,9.4E1,6.5E1,2.9E1,3.2E1,3.3E1,9E0,2.3E1],"tree_param":{"num_deleted":"0","num_feature":"2","num_nodes":"11","size_leaf_vector":"0"}},{"base_weights":[-6.98373E-4,-1.2235381E-3,7.114797E-4,-3.8278431E-3,-1.1010038E-3,-1.26611E-3,-7.0107006E-4],"default_left":[true,true,false,false,true,false,false],"id":17,"leaf_child_counts":[0,0,0,0,0,0,0],"left_children":[1,3,-1,-1,5,-1,-1],"loss_changes":[1.0008484E-4,2.7058966E-5,0E0,0E0,5.3853582E-6,9.1995753E-7,0E0],"parents":[2147483647,0,0,1,1,4,4],"right_children":[2,4,-1,-1,6,-1,-1],"split_conditions":[5.5463635E2,4.6040808E2,2.1344391E-4,-1.148353E-3,5.1251337E2,-3.79833E-4,-2.1032103E-4],"split_indices":[0,0,0,0,0,0,0],"sum_hessian":[1.33E2,9.7E1,3.6E1,3E0,9.4E1,6.5E1,2.9E1],"tree_param":{"num_deleted":"0","num_feature":"2","num_nodes":"7","size_leaf_vector":"0"}},{"base_weights":[-5.0024444E-4,-8.7421946E-4,5.0380424E-4,-2.9665781E-3,-7.7691785E-4,-1.0749251E-3,-6.084868E-4,-6.506428E-4,-1.2069207E-3],"default_left":[true,true,false,false,true,true,false,false,false],"id":18,"leaf_child_counts":[0,0,0,0,0,0,0,0,0],"left_children":[1,3,-1,-1,5,7,-1,-1,-1],"loss_changes":[5.0755978E-5,1.7647028E-5,0E0,0E0,4.1143176E-6,1.0628391E-6,2.140132E-7,0E0,0E0],"parents":[2147483647,0,0,1,1,4,4,5,5],"right_children":[2,4,-1,-1,6,8,-1,-1,-1],"split_conditions":[5.5463635E2,4.6040808E2,1.5114128E-4,-8.899735E-4,4.849944E2,4.641494E2,-1.8254605E-4,-1.9519284E-4,-3.620762E-4],"split_indices":[0,0,0,0,0,0,0,0,0],"sum_hessian":[1.33E2,9.7E1,3.6E1,3E0,9.4E1,3.2E1,6.2E1,9E0,2.3E1],"tree_param":{"num_deleted":"0","num_feature":"2","num_nodes":"9","size_leaf_vector":"0"}},{"base_weights":[-3.6121166E-4,-6.285863E-4,3.567322E-4,-2.2990978E-3,-5.5163226E-4,-7.693345E-4,-4.2884165E-4],"default_left":[true,true,false,false,true,false,false],"id":19,"leaf_child_counts":[0,0,0,0,0,0,0],"left_children":[1,3,-1,-1,5,-1,-1],"loss_changes":[2.594687E-5,1.1329899E-5,0E0,0E0,2.2095956E-6,4.7162393E-7,3.930645E-7],"parents":[2147483647,0,0,1,1,4,4],"right_children":[2,4,-1,-1,6,-1,-1],"split_conditions":[5.5463635E2,4.6040808E2,1.0701967E-4,-6.8972935E-4,4.849944E2,-2.3080036E-4,-1.2865251E-4],"split_indices":[0,0,0,0,0,0,0],"sum_hessian":[1.33E2,9.7E1,3.6E1,3E0,9.4E1,3.2E1,6.2E1],"tree_param":{"num_deleted":"0","num_feature":"2","num_nodes":"7","size_leaf_vector":"0"}},{"base_weights":[-2.5987058E-4,-4.5071528E-4,2.5263347E-4,-1.781801E-3,-3.8992518E-4,-4.9933605E-4,-2.2001889E-4],"default_left":[true,true,false,false,true,false,false],"id":20,"leaf_child_counts":[0,0,0,0,0,0,0],"left_children":[1,3,-1,-1,5,-1,-1],"loss_changes":[1.32202285E-5,7.2350776E-6,0E0,0E0,1.656148E-6,6.519913E-7,0E0],"parents":[2147483647,0,0,1,1,4,4],"right_children":[2,4,-1,-1,6,-1,-1],"split_conditions":[5.5463635E2,4.6040808E2,7.579004E-5,-5.3454033E-4,5.1483276E2,-1.4980082E-4,-6.600567E-5],"split_indices":[0,0,0,0,1,0,0],"sum_hessian":[1.33E2,9.7E1,3.6E1,3E0,9.4E1,5.6E1,3.8E1],"tree_param":{"num_deleted":"0","num_feature":"2","num_nodes":"7","size_leaf_vector":"0"}},{"base_weights":[-1.8694991E-4,-3.2315624E-4,1.7886548E-4,-1.3808956E-3,-2.752182E-4,-4.2312025E-4,-1.9337716E-4],"default_left":[true,true,false,false,true,false,false],"id":21,"leaf_child_counts":[0,0,0,0,0,0,0],"left_children":[1,3,-1,-1,5,-1,-1],"loss_changes":[6.7345345E-6,4.5891366E-6,0E0,0E0,1.0681019E-6,4.0906252E-7,1.4809734E-7],"parents":[2147483647,0,0,1,1,4,4],"right_children":[2,4,-1,-1,6,-1,-1],"split_conditions":[5.5463635E2,4.6040808E2,5.3659645E-5,-4.142687E-4,4.849944E2,-1.2693608E-4,-5.801315E-5],"split_indices":[0,0,0,0,0,0,0],"sum_hessian":[1.33E2,9.7E1,3.6E1,3E0,9.4E1,3.2E1,6.2E1],"tree_param":{"num_deleted":"0","num_feature":"2","num_nodes":"7","size_leaf_vector":"0"}},{"base_weights":[-1.3493301E-4,-2.9646693E-4,3.598777E-5,-1.0701942E-3,-2.4508242E-4],"default_left":[true,true,false,false,false],"id":22,"leaf_child_counts":[0,0,0,0,0],"left_children":[1,3,-1,-1,-1],"loss_changes":[3.7103423E-6,2.480987E-6,6.8633113E-7,0E0,1.9768277E-7],"parents":[2147483647,0,0,1,1],"right_children":[2,4,-1,-1,-1],"split_conditions":[5.1251337E2,4.6040808E2,1.07963315E-5,-3.2105827E-4,-7.352473E-5],"split_indices":[0,0,0,0,0],"sum_hessian":[1.33E2,6.8E1,6.5E1,3E0,6.5E1],"tree_param":{"num_deleted":"0","num_feature":"2","num_nodes":"5","size_leaf_vector":"0"}},{"base_weights":[-9.7317505E-5,-1.7692852E-4,1.16174284E-4,-8.294007E-4,-1.4759359E-4],"default_left":[true,true,false,false,false],"id":23,"leaf_child_counts":[0,0,0,0,0],"left_children":[1,3,-1,-1,-1],"loss_changes":[2.2980585E-6,1.7533271E-6,0E0,0E0,3.221728E-7],"parents":[2147483647,0,0,1,1],"right_children":[2,4,-1,-1,-1],"split_conditions":[5.5463635E2,4.6040808E2,3.4852288E-5,-2.4882023E-4,-4.4278077E-5],"split_indices":[0,0,0,0,0],"sum_hessian":[1.33E2,9.7E1,3.6E1,3E0,9.4E1],"tree_param":{"num_deleted":"0","num_feature":"2","num_nodes":"5","size_leaf_vector":"0"}},{"base_weights":[-7.0054615E-5,-2.4173429E-4,-6.9180146E-6],"default_left":[true,false,false],"id":24,"leaf_child_counts":[0,0,0],"left_children":[1,-1,-1],"loss_changes":[1.45079E-6,7.834253E-7,4.661667E-7],"parents":[2147483647,0,0],"right_children":[2,-1,-1],"split_conditions":[4.849944E2,-7.252029E-5,-2.0754044E-6],"split_indices":[0,0,0],"sum_hessian":[1.33E2,3.5E1,9.8E1],"tree_param":{"num_deleted":"0","num_feature":"2","num_nodes":"3","size_leaf_vector":"0"}},{"base_weights":[-4.959062E-5,-5.883954E-4,-3.276001E-5],"default_left":[true,false,false],"id":25,"leaf_child_counts":[0,0,0],"left_children":[1,-1,-1],"loss_changes":[1.1958914E-6,0E0,7.002418E-7],"parents":[2147483647,0,0],"right_children":[2,-1,-1],"split_conditions":[4.6040808E2,-1.7651863E-4,-9.828003E-6],"split_indices":[0,0,0],"sum_hessian":[1.33E2,3E0,1.3E2],"tree_param":{"num_deleted":"0","num_feature":"2","num_nodes":"3","size_leaf_vector":"0"}},{"base_weights":[-3.610317E-5],"default_left":[false],"id":26,"leaf_child_counts":[0],"left_children":[-1],"loss_changes":[8.558858E-7],"parents":[2147483647],"right_children":[-1],"split_conditions":[-1.0830951E-5],"split_indices":[0],"sum_hessian":[1.33E2],"tree_param":{"num_deleted":"0","num_feature":"2","num_nodes":"1","size_leaf_vector":"0"}},{"base_weights":[-2.5347292E-5],"default_left":[false],"id":27,"leaf_child_counts":[0],"left_children":[-1],"loss_changes":[8.5493843E-7],"parents":[2147483647],"right_children":[-1],"split_conditions":[-7.604188E-6],"split_indices":[0],"sum_hessian":[1.33E2],"tree_param":{"num_deleted":"0","num_feature":"2","num_nodes":"1","size_leaf_vector":"0"}},{"base_weights":[-1.7793418E-5],"default_left":[false],"id":28,"leaf_child_counts":[0],"left_children":[-1],"loss_changes":[8.5427524E-7],"parents":[2147483647],"right_children":[-1],"split_conditions":[-5.3380254E-6],"split_indices":[0],"sum_hessian":[1.33E2],"tree_param":{"num_deleted":"0","num_feature":"2","num_nodes":"1","size_leaf_vector":"0"}},{"base_weights":[-1.2489259E-5],"default_left":[false],"id":29,"leaf_child_counts":[0],"left_children":[-1],"loss_changes":[8.53835E-7],"parents":[2147483647],"right_children":[-1],"split_conditions":[-3.7467778E-6],"split_indices":[0],"sum_hessian":[1.33E2],"tree_param":{"num_deleted":"0","num_feature":"2","num_nodes":"1","size_leaf_vector":"0"}},{"base_weights":[-8.767978E-6],"default_left":[false],"id":30,"leaf_child_counts":[0],"left_children":[-1],"loss_changes":[8.534694E-7],"parents":[2147483647],"right_children":[-1],"split_conditions":[-2.6303935E-6],"split_indices":[0],"sum_hessian":[1.33E2],"tree_param":{"num_deleted":"0","num_feature":"2","num_nodes":"1","size_leaf_vector":"0"}},{"base_weights":[-6.158044E-6],"default_left":[false],"id":31,"leaf_child_counts":[0],"left_children":[-1],"loss_changes":[8.5299524E-7],"parents":[2147483647],"right_children":[-1],"split_conditions":[-1.8474133E-6],"split_indices":[0],"sum_hessian":[1.33E2],"tree_param":{"num_deleted":"0","num_feature":"2","num_nodes":"1","size_leaf_vector":"0"}},{"base_weights":[-4.3254304E-6],"default_left":[false],"id":32,"leaf_child_counts":[0],"left_children":[-1],"loss_changes":[8.526493E-7],"parents":[2147483647],"right_children":[-1],"split_conditions":[-1.2976292E-6],"split_indices":[0],"sum_hessian":[1.33E2],"tree_param":{"num_deleted":"0","num_feature":"2","num_nodes":"1","size_leaf_vector":"0"}},{"base_weights":[-3.0344574E-6],"default_left":[false],"id":33,"leaf_child_counts":[0],"left_children":[-1],"loss_changes":[8.5258563E-7],"parents":[2147483647],"right_children":[-1],"split_conditions":[-9.103373E-7],"split_indices":[0],"sum_hessian":[1.33E2],"tree_param":{"num_deleted":"0","num_feature":"2","num_nodes":"1","size_leaf_vector":"0"}},{"base_weights":[-2.1347234E-6],"default_left":[false],"id":34,"leaf_child_counts":[0],"left_children":[-1],"loss_changes":[8.523698E-7],"parents":[2147483647],"right_children":[-1],"split_conditions":[-6.4041706E-7],"split_indices":[0],"sum_hessian":[1.33E2],"tree_param":{"num_deleted":"0","num_feature":"2","num_nodes":"1","size_leaf_vector":"0"}},{"base_weights":[-1.4960933E-6],"default_left":[false],"id":35,"leaf_child_counts":[0],"left_children":[-1],"loss_changes":[8.5234035E-7],"parents":[2147483647],"right_children":[-1],"split_conditions":[-4.4882802E-7],"split_indices":[0],"sum_hessian":[1.33E2],"tree_param":{"num_deleted":"0","num_feature":"2","num_nodes":"1","size_leaf_vector":"0"}},{"base_weights":[-1.0447772E-6],"default_left":[false],"id":36,"leaf_child_counts":[0],"left_children":[-1],"loss_changes":[8.525521E-7],"parents":[2147483647],"right_children":[-1],"split_conditions":[-3.1343316E-7],"split_indices":[0],"sum_hessian":[1.33E2],"tree_param":{"num_deleted":"0","num_feature":"2","num_nodes":"1","size_leaf_vector":"0"}},{"base_weights":[-7.3596726E-7],"default_left":[false],"id":37,"leaf_child_counts":[0],"left_children":[-1],"loss_changes":[8.524193E-7],"parents":[2147483647],"right_children":[-1],"split_conditions":[-2.2079018E-7],"split_indices":[0],"sum_hessian":[1.33E2],"tree_param":{"num_deleted":"0","num_feature":"2","num_nodes":"1","size_leaf_vector":"0"}},{"base_weights":[-5.1059413E-7],"default_left":[false],"id":38,"leaf_child_counts":[0],"left_children":[-1],"loss_changes":[8.525286E-7],"parents":[2147483647],"right_children":[-1],"split_conditions":[-1.5317825E-7],"split_indices":[0],"sum_hessian":[1.33E2],"tree_param":{"num_deleted":"0","num_feature":"2","num_nodes":"1","size_leaf_vector":"0"}},{"base_weights":[-3.5393037E-7],"default_left":[false],"id":39,"leaf_child_counts":[0],"left_children":[-1],"loss_changes":[8.5268744E-7],"parents":[2147483647],"right_children":[-1],"split_conditions":[-1.06179115E-7],"split_indices":[0],"sum_hessian":[1.33E2],"tree_param":{"num_deleted":"0","num_feature":"2","num_nodes":"1","size_leaf_vector":"0"}},{"base_weights":[-2.4581357E-7],"default_left":[false],"id":40,"leaf_child_counts":[0],"left_children":[-1],"loss_changes":[8.5280186E-7],"parents":[2147483647],"right_children":[-1],"split_conditions":[-7.3744076E-8],"split_indices":[0],"sum_hessian":[1.33E2],"tree_param":{"num_deleted":"0","num_feature":"2","num_nodes":"1","size_leaf_vector":"0"}},{"base_weights":[-1.7554736E-7],"default_left":[false],"id":41,"leaf_child_counts":[0],"left_children":[-1],"loss_changes":[8.526469E-7],"parents":[2147483647],"right_children":[-1],"split_conditions":[-5.266421E-8],"split_indices":[0],"sum_hessian":[1.33E2],"tree_param":{"num_deleted":"0","num_feature":"2","num_nodes":"1","size_leaf_vector":"0"}},{"base_weights":[-1.2049507E-7],"default_left":[false],"id":42,"leaf_child_counts":[0],"left_children":[-1],"loss_changes":[8.526911E-7],"parents":[2147483647],"right_children":[-1],"split_conditions":[-3.6148524E-8],"split_indices":[0],"sum_hessian":[1.33E2],"tree_param":{"num_deleted":"0","num_feature":"2","num_nodes":"1","size_leaf_vector":"0"}},{"base_weights":[-7.7702886E-8],"default_left":[false],"id":43,"leaf_child_counts":[0],"left_children":[-1],"loss_changes":[8.5298075E-7],"parents":[2147483647],"right_children":[-1],"split_conditions":[-2.3310866E-8],"split_indices":[0],"sum_hessian":[1.33E2],"tree_param":{"num_deleted":"0","num_feature":"2","num_nodes":"1","size_leaf_vector":"0"}},{"base_weights":[-5.9111184E-8],"default_left":[false],"id":44,"leaf_child_counts":[0],"left_children":[-1],"loss_changes":[8.527374E-7],"parents":[2147483647],"right_children":[-1],"split_conditions":[-1.7733356E-8],"split_indices":[0],"sum_hessian":[1.33E2],"tree_param":{"num_deleted":"0","num_feature":"2","num_nodes":"1","size_leaf_vector":"0"}},{"base_weights":[-4.7539153E-8],"default_left":[false],"id":45,"leaf_child_counts":[0],"left_children":[-1],"loss_changes":[8.5258597E-7],"parents":[2147483647],"right_children":[-1],"split_conditions":[-1.42617465E-8],"split_indices":[0],"sum_hessian":[1.33E2],"tree_param":{"num_deleted":"0","num_feature":"2","num_nodes":"1","size_leaf_vector":"0"}},{"base_weights":[-3.71139E-8],"default_left":[false],"id":46,"leaf_child_counts":[0],"left_children":[-1],"loss_changes":[8.5244955E-7],"parents":[2147483647],"right_children":[-1],"split_conditions":[-1.113417E-8],"split_indices":[0],"sum_hessian":[1.33E2],"tree_param":{"num_deleted":"0","num_feature":"2","num_nodes":"1","size_leaf_vector":"0"}},{"base_weights":[-2.930191E-8],"default_left":[false],"id":47,"leaf_child_counts":[0],"left_children":[-1],"loss_changes":[8.523473E-7],"parents":[2147483647],"right_children":[-1],"split_conditions":[-8.790574E-9],"split_indices":[0],"sum_hessian":[1.33E2],"tree_param":{"num_deleted":"0","num_feature":"2","num_nodes":"1","size_leaf_vector":"0"}},{"base_weights":[-2.2129337E-8],"default_left":[false],"id":48,"leaf_child_counts":[0],"left_children":[-1],"loss_changes":[8.5225344E-7],"parents":[2147483647],"right_children":[-1],"split_conditions":[-6.638801E-9],"split_indices":[0],"sum_hessian":[1.33E2],"tree_param":{"num_deleted":"0","num_feature":"2","num_nodes":"1","size_leaf_vector":"0"}},{"base_weights":[-1.8508299E-8],"default_left":[false],"id":49,"leaf_child_counts":[0],"left_children":[-1],"loss_changes":[8.52206E-7],"parents":[2147483647],"right_children":[-1],"split_conditions":[-5.55249E-9],"split_indices":[0],"sum_hessian":[1.33E2],"tree_param":{"num_deleted":"0","num_feature":"2","num_nodes":"1","size_leaf_vector":"0"}},{"base_weights":[-1.5478026E-8],"default_left":[false],"id":50,"leaf_child_counts":[0],"left_children":[-1],"loss_changes":[8.521664E-7],"parents":[2147483647],"right_children":[-1],"split_conditions":[-4.643408E-9],"split_indices":[0],"sum_hessian":[1.33E2],"tree_param":{"num_deleted":"0","num_feature":"2","num_nodes":"1","size_leaf_vector":"0"}},{"base_weights":[-1.23712995E-8],"default_left":[false],"id":51,"leaf_child_counts":[0],"left_children":[-1],"loss_changes":[8.521258E-7],"parents":[2147483647],"right_children":[-1],"split_conditions":[-3.71139E-9],"split_indices":[0],"sum_hessian":[1.33E2],"tree_param":{"num_deleted":"0","num_feature":"2","num_nodes":"1","size_leaf_vector":"0"}},{"base_weights":[-1.1342675E-8],"default_left":[false],"id":52,"leaf_child_counts":[0],"left_children":[-1],"loss_changes":[8.5211235E-7],"parents":[2147483647],"right_children":[-1],"split_conditions":[-3.4028027E-9],"split_indices":[0],"sum_hessian":[1.33E2],"tree_param":{"num_deleted":"0","num_feature":"2","num_nodes":"1","size_leaf_vector":"0"}},{"base_weights":[-1.0439153E-8],"default_left":[false],"id":53,"leaf_child_counts":[0],"left_children":[-1],"loss_changes":[8.521005E-7],"parents":[2147483647],"right_children":[-1],"split_conditions":[-3.131746E-9],"split_indices":[0],"sum_hessian":[1.33E2],"tree_param":{"num_deleted":"0","num_feature":"2","num_nodes":"1","size_leaf_vector":"0"}},{"base_weights":[-9.751086E-9],"default_left":[false],"id":54,"leaf_child_counts":[0],"left_children":[-1],"loss_changes":[8.520915E-7],"parents":[2147483647],"right_children":[-1],"split_conditions":[-2.925326E-9],"split_indices":[0],"sum_hessian":[1.33E2],"tree_param":{"num_deleted":"0","num_feature":"2","num_nodes":"1","size_leaf_vector":"0"}},{"base_weights":[-8.8406145E-9],"default_left":[false],"id":55,"leaf_child_counts":[0],"left_children":[-1],"loss_changes":[8.520796E-7],"parents":[2147483647],"right_children":[-1],"split_conditions":[-2.6521845E-9],"split_indices":[0],"sum_hessian":[1.33E2],"tree_param":{"num_deleted":"0","num_feature":"2","num_nodes":"1","size_leaf_vector":"0"}},{"base_weights":[-7.971844E-9],"default_left":[false],"id":56,"leaf_child_counts":[0],"left_children":[-1],"loss_changes":[8.5206824E-7],"parents":[2147483647],"right_children":[-1],"split_conditions":[-2.3915532E-9],"split_indices":[0],"sum_hessian":[1.33E2],"tree_param":{"num_deleted":"0","num_feature":"2","num_nodes":"1","size_leaf_vector":"0"}},{"base_weights":[-7.2698763E-9],"default_left":[false],"id":57,"leaf_child_counts":[0],"left_children":[-1],"loss_changes":[8.5205903E-7],"parents":[2147483647],"right_children":[-1],"split_conditions":[-2.180963E-9],"split_indices":[0],"sum_hessian":[1.33E2],"tree_param":{"num_deleted":"0","num_feature":"2","num_nodes":"1","size_leaf_vector":"0"}},{"base_weights":[-6.6999624E-9],"default_left":[false],"id":58,"leaf_child_counts":[0],"left_children":[-1],"loss_changes":[8.520516E-7],"parents":[2147483647],"right_children":[-1],"split_conditions":[-2.0099888E-9],"split_indices":[0],"sum_hessian":[1.33E2],"tree_param":{"num_deleted":"0","num_feature":"2","num_nodes":"1","size_leaf_vector":"0"}},{"base_weights":[-6.0327463E-9],"default_left":[false],"id":59,"leaf_child_counts":[0],"left_children":[-1],"loss_changes":[8.5204283E-7],"parents":[2147483647],"right_children":[-1],"split_conditions":[-1.809824E-9],"split_indices":[0],"sum_hessian":[1.33E2],"tree_param":{"num_deleted":"0","num_feature":"2","num_nodes":"1","size_leaf_vector":"0"}},{"base_weights":[-5.6713376E-9],"default_left":[false],"id":60,"leaf_child_counts":[0],"left_children":[-1],"loss_changes":[8.520381E-7],"parents":[2147483647],"right_children":[-1],"split_conditions":[-1.7014014E-9],"split_indices":[0],"sum_hessian":[1.33E2],"tree_param":{"num_deleted":"0","num_feature":"2","num_nodes":"1","size_leaf_vector":"0"}},{"base_weights":[-5.3099285E-9],"default_left":[false],"id":61,"leaf_child_counts":[0],"left_children":[-1],"loss_changes":[8.520334E-7],"parents":[2147483647],"right_children":[-1],"split_conditions":[-1.5929786E-9],"split_indices":[0],"sum_hessian":[1.33E2],"tree_param":{"num_deleted":"0","num_feature":"2","num_nodes":"1","size_leaf_vector":"0"}},{"base_weights":[-4.9624203E-9],"default_left":[false],"id":62,"leaf_child_counts":[0],"left_children":[-1],"loss_changes":[8.5202885E-7],"parents":[2147483647],"right_children":[-1],"split_conditions":[-1.4887261E-9],"split_indices":[0],"sum_hessian":[1.33E2],"tree_param":{"num_deleted":"0","num_feature":"2","num_nodes":"1","size_leaf_vector":"0"}},{"base_weights":[-4.614912E-9],"default_left":[false],"id":63,"leaf_child_counts":[0],"left_children":[-1],"loss_changes":[8.520243E-7],"parents":[2147483647],"right_children":[-1],"split_conditions":[-1.3844736E-9],"split_indices":[0],"sum_hessian":[1.33E2],"tree_param":{"num_deleted":"0","num_feature":"2","num_nodes":"1","size_leaf_vector":"0"}},{"base_weights":[-4.3925064E-9],"default_left":[false],"id":64,"leaf_child_counts":[0],"left_children":[-1],"loss_changes":[8.520214E-7],"parents":[2147483647],"right_children":[-1],"split_conditions":[-1.3177519E-9],"split_indices":[0],"sum_hessian":[1.33E2],"tree_param":{"num_deleted":"0","num_feature":"2","num_nodes":"1","size_leaf_vector":"0"}},{"base_weights":[-4.2257025E-9],"default_left":[false],"id":65,"leaf_child_counts":[0],"left_children":[-1],"loss_changes":[8.520192E-7],"parents":[2147483647],"right_children":[-1],"split_conditions":[-1.2677108E-9],"split_indices":[0],"sum_hessian":[1.33E2],"tree_param":{"num_deleted":"0","num_feature":"2","num_nodes":"1","size_leaf_vector":"0"}},{"base_weights":[-4.0936494E-9],"default_left":[false],"id":66,"leaf_child_counts":[0],"left_children":[-1],"loss_changes":[8.520175E-7],"parents":[2147483647],"right_children":[-1],"split_conditions":[-1.2280948E-9],"split_indices":[0],"sum_hessian":[1.33E2],"tree_param":{"num_deleted":"0","num_feature":"2","num_nodes":"1","size_leaf_vector":"0"}},{"base_weights":[-3.8503933E-9],"default_left":[false],"id":67,"leaf_child_counts":[0],"left_children":[-1],"loss_changes":[8.520143E-7],"parents":[2147483647],"right_children":[-1],"split_conditions":[-1.155118E-9],"split_indices":[0],"sum_hessian":[1.33E2],"tree_param":{"num_deleted":"0","num_feature":"2","num_nodes":"1","size_leaf_vector":"0"}},{"base_weights":[-3.6349381E-9],"default_left":[false],"id":68,"leaf_child_counts":[0],"left_children":[-1],"loss_changes":[8.5201145E-7],"parents":[2147483647],"right_children":[-1],"split_conditions":[-1.0904815E-9],"split_indices":[0],"sum_hessian":[1.33E2],"tree_param":{"num_deleted":"0","num_feature":"2","num_nodes":"1","size_leaf_vector":"0"}},{"base_weights":[-3.4889847E-9],"default_left":[false],"id":69,"leaf_child_counts":[0],"left_children":[-1],"loss_changes":[8.520096E-7],"parents":[2147483647],"right_children":[-1],"split_conditions":[-1.0466954E-9],"split_indices":[0],"sum_hessian":[1.33E2],"tree_param":{"num_deleted":"0","num_feature":"2","num_nodes":"1","size_leaf_vector":"0"}},{"base_weights":[-3.3569314E-9],"default_left":[false],"id":70,"leaf_child_counts":[0],"left_children":[-1],"loss_changes":[8.520078E-7],"parents":[2147483647],"right_children":[-1],"split_conditions":[-1.0070794E-9],"split_indices":[0],"sum_hessian":[1.33E2],"tree_param":{"num_deleted":"0","num_feature":"2","num_nodes":"1","size_leaf_vector":"0"}},{"base_weights":[-3.1275758E-9],"default_left":[false],"id":71,"leaf_child_counts":[0],"left_children":[-1],"loss_changes":[8.5200486E-7],"parents":[2147483647],"right_children":[-1],"split_conditions":[-9.382728E-10],"split_indices":[0],"sum_hessian":[1.33E2],"tree_param":{"num_deleted":"0","num_feature":"2","num_nodes":"1","size_leaf_vector":"0"}},{"base_weights":[-2.9121205E-9],"default_left":[false],"id":72,"leaf_child_counts":[0],"left_children":[-1],"loss_changes":[8.52002E-7],"parents":[2147483647],"right_children":[-1],"split_conditions":[-8.736362E-10],"split_indices":[0],"sum_hessian":[1.33E2],"tree_param":{"num_deleted":"0","num_feature":"2","num_nodes":"1","size_leaf_vector":"0"}},{"base_weights":[-2.766167E-9],"default_left":[false],"id":73,"leaf_child_counts":[0],"left_children":[-1],"loss_changes":[8.520001E-7],"parents":[2147483647],"right_children":[-1],"split_conditions":[-8.2985013E-10],"split_indices":[0],"sum_hessian":[1.33E2],"tree_param":{"num_deleted":"0","num_feature":"2","num_nodes":"1","size_leaf_vector":"0"}},{"base_weights":[-2.6341138E-9],"default_left":[false],"id":74,"leaf_child_counts":[0],"left_children":[-1],"loss_changes":[8.519984E-7],"parents":[2147483647],"right_children":[-1],"split_conditions":[-7.9023416E-10],"split_indices":[0],"sum_hessian":[1.33E2],"tree_param":{"num_deleted":"0","num_feature":"2","num_nodes":"1","size_leaf_vector":"0"}},{"base_weights":[-2.4047584E-9],"default_left":[false],"id":75,"leaf_child_counts":[0],"left_children":[-1],"loss_changes":[8.5199537E-7],"parents":[2147483647],"right_children":[-1],"split_conditions":[-7.2142753E-10],"split_indices":[0],"sum_hessian":[1.33E2],"tree_param":{"num_deleted":"0","num_feature":"2","num_nodes":"1","size_leaf_vector":"0"}},{"base_weights":[-2.189303E-9],"default_left":[false],"id":76,"leaf_child_counts":[0],"left_children":[-1],"loss_changes":[8.519926E-7],"parents":[2147483647],"right_children":[-1],"split_conditions":[-6.567909E-10],"split_indices":[0],"sum_hessian":[1.33E2],"tree_param":{"num_deleted":"0","num_feature":"2","num_nodes":"1","size_leaf_vector":"0"}},{"base_weights":[-2.0502997E-9],"default_left":[false],"id":77,"leaf_child_counts":[0],"left_children":[-1],"loss_changes":[8.5199076E-7],"parents":[2147483647],"right_children":[-1],"split_conditions":[-6.150899E-10],"split_indices":[0],"sum_hessian":[1.33E2],"tree_param":{"num_deleted":"0","num_feature":"2","num_nodes":"1","size_leaf_vector":"0"}},{"base_weights":[-1.939097E-9],"default_left":[false],"id":78,"leaf_child_counts":[0],"left_children":[-1],"loss_changes":[8.519893E-7],"parents":[2147483647],"right_children":[-1],"split_conditions":[-5.8172916E-10],"split_indices":[0],"sum_hessian":[1.33E2],"tree_param":{"num_deleted":"0","num_feature":"2","num_nodes":"1","size_leaf_vector":"0"}},{"base_weights":[-1.7097415E-9],"default_left":[false],"id":79,"leaf_child_counts":[0],"left_children":[-1],"loss_changes":[8.5198633E-7],"parents":[2147483647],"right_children":[-1],"split_conditions":[-5.129225E-10],"split_indices":[0],"sum_hessian":[1.33E2],"tree_param":{"num_deleted":"0","num_feature":"2","num_nodes":"1","size_leaf_vector":"0"}},{"base_weights":[-1.5081866E-9],"default_left":[false],"id":80,"leaf_child_counts":[0],"left_children":[-1],"loss_changes":[8.5198366E-7],"parents":[2147483647],"right_children":[-1],"split_conditions":[-4.52456E-10],"split_indices":[0],"sum_hessian":[1.33E2],"tree_param":{"num_deleted":"0","num_feature":"2","num_nodes":"1","size_leaf_vector":"0"}},{"base_weights":[-1.5012364E-9],"default_left":[false],"id":81,"leaf_child_counts":[0],"left_children":[-1],"loss_changes":[8.519836E-7],"parents":[2147483647],"right_children":[-1],"split_conditions":[-4.5037093E-10],"split_indices":[0],"sum_hessian":[1.33E2],"tree_param":{"num_deleted":"0","num_feature":"2","num_nodes":"1","size_leaf_vector":"0"}},{"base_weights":[-1.4942863E-9],"default_left":[false],"id":82,"leaf_child_counts":[0],"left_children":[-1],"loss_changes":[8.519835E-7],"parents":[2147483647],"right_children":[-1],"split_conditions":[-4.4828588E-10],"split_indices":[0],"sum_hessian":[1.33E2],"tree_param":{"num_deleted":"0","num_feature":"2","num_nodes":"1","size_leaf_vector":"0"}},{"base_weights":[-1.4803859E-9],"default_left":[false],"id":83,"leaf_child_counts":[0],"left_children":[-1],"loss_changes":[8.5198326E-7],"parents":[2147483647],"right_children":[-1],"split_conditions":[-4.441158E-10],"split_indices":[0],"sum_hessian":[1.33E2],"tree_param":{"num_deleted":"0","num_feature":"2","num_nodes":"1","size_leaf_vector":"0"}},{"base_weights":[-1.4664856E-9],"default_left":[false],"id":84,"leaf_child_counts":[0],"left_children":[-1],"loss_changes":[8.5198315E-7],"parents":[2147483647],"right_children":[-1],"split_conditions":[-4.399457E-10],"split_indices":[0],"sum_hessian":[1.33E2],"tree_param":{"num_deleted":"0","num_feature":"2","num_nodes":"1","size_leaf_vector":"0"}},{"base_weights":[-1.4595354E-9],"default_left":[false],"id":85,"leaf_child_counts":[0],"left_children":[-1],"loss_changes":[8.5198303E-7],"parents":[2147483647],"right_children":[-1],"split_conditions":[-4.3786064E-10],"split_indices":[0],"sum_hessian":[1.33E2],"tree_param":{"num_deleted":"0","num_feature":"2","num_nodes":"1","size_leaf_vector":"0"}},{"base_weights":[-1.4525852E-9],"default_left":[false],"id":86,"leaf_child_counts":[0],"left_children":[-1],"loss_changes":[8.519829E-7],"parents":[2147483647],"right_children":[-1],"split_conditions":[-4.3577555E-10],"split_indices":[0],"sum_hessian":[1.33E2],"tree_param":{"num_deleted":"0","num_feature":"2","num_nodes":"1","size_leaf_vector":"0"}},{"base_weights":[-1.4386848E-9],"default_left":[false],"id":87,"leaf_child_counts":[0],"left_children":[-1],"loss_changes":[8.5198275E-7],"parents":[2147483647],"right_children":[-1],"split_conditions":[-4.3160547E-10],"split_indices":[0],"sum_hessian":[1.33E2],"tree_param":{"num_deleted":"0","num_feature":"2","num_nodes":"1","size_leaf_vector":"0"}},{"base_weights":[-1.4247845E-9],"default_left":[false],"id":88,"leaf_child_counts":[0],"left_children":[-1],"loss_changes":[8.519826E-7],"parents":[2147483647],"right_children":[-1],"split_conditions":[-4.2743536E-10],"split_indices":[0],"sum_hessian":[1.33E2],"tree_param":{"num_deleted":"0","num_feature":"2","num_nodes":"1","size_leaf_vector":"0"}},{"base_weights":[-1.4178344E-9],"default_left":[false],"id":89,"leaf_child_counts":[0],"left_children":[-1],"loss_changes":[8.5198246E-7],"parents":[2147483647],"right_children":[-1],"split_conditions":[-4.2535034E-10],"split_indices":[0],"sum_hessian":[1.33E2],"tree_param":{"num_deleted":"0","num_feature":"2","num_nodes":"1","size_leaf_vector":"0"}},{"base_weights":[-1.4108842E-9],"default_left":[false],"id":90,"leaf_child_counts":[0],"left_children":[-1],"loss_changes":[8.5198235E-7],"parents":[2147483647],"right_children":[-1],"split_conditions":[-4.2326528E-10],"split_indices":[0],"sum_hessian":[1.33E2],"tree_param":{"num_deleted":"0","num_feature":"2","num_nodes":"1","size_leaf_vector":"0"}},{"base_weights":[-1.3969839E-9],"default_left":[false],"id":91,"leaf_child_counts":[0],"left_children":[-1],"loss_changes":[8.5198224E-7],"parents":[2147483647],"right_children":[-1],"split_conditions":[-4.1909518E-10],"split_indices":[0],"sum_hessian":[1.33E2],"tree_param":{"num_deleted":"0","num_feature":"2","num_nodes":"1","size_leaf_vector":"0"}},{"base_weights":[-1.3830835E-9],"default_left":[false],"id":92,"leaf_child_counts":[0],"left_children":[-1],"loss_changes":[8.51982E-7],"parents":[2147483647],"right_children":[-1],"split_conditions":[-4.1492507E-10],"split_indices":[0],"sum_hessian":[1.33E2],"tree_param":{"num_deleted":"0","num_feature":"2","num_nodes":"1","size_leaf_vector":"0"}},{"base_weights":[-1.3761333E-9],"default_left":[false],"id":93,"leaf_child_counts":[0],"left_children":[-1],"loss_changes":[8.519819E-7],"parents":[2147483647],"right_children":[-1],"split_conditions":[-4.1284E-10],"split_indices":[0],"sum_hessian":[1.33E2],"tree_param":{"num_deleted":"0","num_feature":"2","num_nodes":"1","size_leaf_vector":"0"}},{"base_weights":[-1.3691832E-9],"default_left":[false],"id":94,"leaf_child_counts":[0],"left_children":[-1],"loss_changes":[8.5198184E-7],"parents":[2147483647],"right_children":[-1],"split_conditions":[-4.1075499E-10],"split_indices":[0],"sum_hessian":[1.33E2],"tree_param":{"num_deleted":"0","num_feature":"2","num_nodes":"1","size_leaf_vector":"0"}},{"base_weights":[-1.3552829E-9],"default_left":[false],"id":95,"leaf_child_counts":[0],"left_children":[-1],"loss_changes":[8.5198167E-7],"parents":[2147483647],"right_children":[-1],"split_conditions":[-4.0658488E-10],"split_indices":[0],"sum_hessian":[1.33E2],"tree_param":{"num_deleted":"0","num_feature":"2","num_nodes":"1","size_leaf_vector":"0"}},{"base_weights":[-1.3413826E-9],"default_left":[false],"id":96,"leaf_child_counts":[0],"left_children":[-1],"loss_changes":[8.5198144E-7],"parents":[2147483647],"right_children":[-1],"split_conditions":[-4.024148E-10],"split_indices":[0],"sum_hessian":[1.33E2],"tree_param":{"num_deleted":"0","num_feature":"2","num_nodes":"1","size_leaf_vector":"0"}},{"base_weights":[-1.3344323E-9],"default_left":[false],"id":97,"leaf_child_counts":[0],"left_children":[-1],"loss_changes":[8.519814E-7],"parents":[2147483647],"right_children":[-1],"split_conditions":[-4.003297E-10],"split_indices":[0],"sum_hessian":[1.33E2],"tree_param":{"num_deleted":"0","num_feature":"2","num_nodes":"1","size_leaf_vector":"0"}},{"base_weights":[-1.3274821E-9],"default_left":[false],"id":98,"leaf_child_counts":[0],"left_children":[-1],"loss_changes":[8.519813E-7],"parents":[2147483647],"right_children":[-1],"split_conditions":[-3.9824466E-10],"split_indices":[0],"sum_hessian":[1.33E2],"tree_param":{"num_deleted":"0","num_feature":"2","num_nodes":"1","size_leaf_vector":"0"}},{"base_weights":[-1.3135818E-9],"default_left":[false],"id":99,"leaf_child_counts":[0],"left_children":[-1],"loss_changes":[8.519811E-7],"parents":[2147483647],"right_children":[-1],"split_conditions":[-3.9407455E-10],"split_indices":[0],"sum_hessian":[1.33E2],"tree_param":{"num_deleted":"0","num_feature":"2","num_nodes":"1","size_leaf_vector":"0"}}]},"name":"gbtree"},"learner_model_param":{"base_score":"5E-1","num_class":"0","num_feature":"2"},"objective":{"name":"reg:squarederror","reg_loss_param":{"scale_pos_weight":"1"}}},"version":[1,2,1]}